{"hall": "楽園池袋店グリーンサイド", "rows": [{"m": 6, "d": 8, "kishu": "スマスロモンキーターンV", "samai": 2431, "g": 8556, "deri": 109.5}, {"m": 6, "d": 8, "kishu": "スマスロヨルムンガンド", "samai": 2153, "g": 2112, "deri": 134.0}, {"m": 6, "d": 8, "kishu": "スマスロバジリスク～甲賀忍法帖～絆2 天膳 BLACK EDITION", "samai": 2073, "g": 3771, "deri": 118.3}, {"m": 6, "d": 8, "kishu": "L無職転生～異世界行ったら本気だす～", "samai": 1920, "g": 4676, "deri": 113.7}, {"m": 6, "d": 8, "kishu": "L戦国乙女5 業火を穿つ宿焔の双刃", "samai": 1494, "g": 7898, "deri": 106.3}, {"m": 6, "d": 8, "kishu": "スマスロ 甲鉄城のカバネリ 海門決戦", "samai": 1305, "g": 5890, "deri": 107.4}, {"m": 6, "d": 8, "kishu": "Lパチスロ かぐや様は告らせたい", "samai": 1074, "g": 1441, "deri": 124.9}, {"m": 6, "d": 8, "kishu": "L ToLOVEるダークネス TRANCE ver.8.7", "samai": 1063, "g": 4954, "deri": 107.1}, {"m": 6, "d": 8, "kishu": "L東京喰種", "samai": 957, "g": 7176, "deri": 104.4}, {"m": 6, "d": 8, "kishu": "スロット ソードアート・オンラインⅡ", "samai": 867, "g": 9339, "deri": 103.1}, {"m": 6, "d": 8, "kishu": "スマスロ スーパーリオエース2", "samai": 691, "g": 2841, "deri": 108.1}, {"m": 6, "d": 8, "kishu": "ファンキージャグラー２ＫＴ", "samai": 537, "g": 5678, "deri": 103.2}, {"m": 6, "d": 8, "kishu": "もっと！クレアの秘宝伝　女神の歌声と太陽の子供達", "samai": 473, "g": 1768, "deri": 108.9}, {"m": 6, "d": 8, "kishu": "ネオアイムジャグラーEX", "samai": 336, "g": 4440, "deri": 102.5}, {"m": 6, "d": 8, "kishu": "スマスロ マギアレコード 魔法少女まどか☆マギカ外伝", "samai": 317, "g": 2997, "deri": 103.5}, {"m": 6, "d": 8, "kishu": "Lパチスロうみねこのなく頃に2", "samai": 217, "g": 4048, "deri": 101.8}, {"m": 6, "d": 8, "kishu": "Lパチスロ炎炎ノ消防隊2", "samai": 210, "g": 8231, "deri": 100.9}, {"m": 6, "d": 8, "kishu": "SHAKE BONUS TRIGGER", "samai": 197, "g": 1745, "deri": 103.8}, {"m": 6, "d": 8, "kishu": "ハッピージャグラーＶＩＩＩ", "samai": 127, "g": 2944, "deri": 101.4}, {"m": 6, "d": 8, "kishu": "A-SLOT+異世界かるてっとBT", "samai": 77, "g": 2012, "deri": 101.3}, {"m": 6, "d": 8, "kishu": "スマスロ モンスターハンターライズ", "samai": 50, "g": 1291, "deri": 101.3}, {"m": 6, "d": 8, "kishu": "LBスロットGALFY", "samai": 45, "g": 2247, "deri": 100.7}, {"m": 6, "d": 8, "kishu": "スマスロ化物語", "samai": 0, "g": 4527, "deri": 100.0}, {"m": 6, "d": 8, "kishu": "プリズムナナ", "samai": -15, "g": 3047, "deri": 99.8}, {"m": 6, "d": 8, "kishu": "ジャグラーガールズSS", "samai": -55, "g": 3573, "deri": 99.5}, {"m": 6, "d": 8, "kishu": "Lスマスロ北斗の拳", "samai": -56, "g": 1505, "deri": 98.8}, {"m": 6, "d": 8, "kishu": "マイジャグラーV", "samai": -98, "g": 4726, "deri": 99.3}, {"m": 6, "d": 8, "kishu": "ウルトラミラクルジャグラー", "samai": -100, "g": 4459, "deri": 99.0}, {"m": 6, "d": 8, "kishu": "新ハナビ", "samai": -250, "g": 2429, "deri": 96.1}, {"m": 6, "d": 8, "kishu": "ゴーゴージャグラー３", "samai": -250, "g": 4055, "deri": 97.5}, {"m": 6, "d": 8, "kishu": "Lパチスロ革命機ヴァルヴレイヴ2", "samai": -250, "g": 3506, "deri": 95.6}, {"m": 6, "d": 8, "kishu": "Lパチスロ 機動戦士ガンダムユニコーン 覚醒DRIVE", "samai": -250, "g": 971, "deri": 83.4}, {"m": 6, "d": 8, "kishu": "A-SLOT+ ディスクアップ ULTRAREMIX", "samai": -500, "g": 4283, "deri": 96.0}, {"m": 6, "d": 8, "kishu": "スマスロ サンダーV", "samai": -500, "g": 1732, "deri": 88.6}, {"m": 6, "d": 8, "kishu": "スマスロ 東京リベンジャーズ", "samai": -500, "g": 1198, "deri": 82.5}, {"m": 6, "d": 8, "kishu": "Lパチスロからくりサーカス", "samai": -500, "g": 741, "deri": 69.3}, {"m": 6, "d": 8, "kishu": "Lタクトオーパス デスティニー", "samai": -500, "g": 5367, "deri": 95.4}, {"m": 6, "d": 8, "kishu": "パチスロひぐらしのなく頃に祭２", "samai": -750, "g": 1932, "deri": 85.9}, {"m": 6, "d": 8, "kishu": "スマスロ北斗の拳 転生の章2", "samai": -750, "g": 2340, "deri": 87.5}, {"m": 6, "d": 8, "kishu": "スマスロ 攻殻機動隊", "samai": -750, "g": 3721, "deri": 92.1}, {"m": 6, "d": 8, "kishu": "スマスロ ゴッドイーター リザレクション", "samai": -750, "g": 2718, "deri": 88.1}, {"m": 6, "d": 8, "kishu": "スマスロ バイオハザードRE:3", "samai": -750, "g": 2431, "deri": 86.4}, {"m": 6, "d": 8, "kishu": "スマスロ ミリオンゴッド-神々の軌跡-", "samai": -1000, "g": 6027, "deri": 94.4}, {"m": 6, "d": 8, "kishu": "アレックス ブライト", "samai": -1000, "g": 2497, "deri": 85.4}, {"m": 6, "d": 8, "kishu": "L虚構推理", "samai": -1500, "g": 3737, "deri": 85.8}, {"m": 6, "d": 8, "kishu": "1", "samai": 63, "g": 4479, "deri": 100.5}, {"m": 6, "d": 8, "kishu": "4", "samai": 753, "g": 4536, "deri": 105.5}, {"m": 6, "d": 8, "kishu": "6", "samai": 503, "g": 4195, "deri": 104.0}, {"m": 6, "d": 8, "kishu": "7", "samai": 86, "g": 3804, "deri": 100.8}, {"m": 6, "d": 8, "kishu": "8", "samai": 528, "g": 4088, "deri": 104.3}, {"m": 6, "d": 8, "kishu": "9", "samai": 1096, "g": 4546, "deri": 108.0}, {"m": 6, "d": 7, "kishu": "スマスロバジリスク～甲賀忍法帖～絆2 天膳 BLACK EDITION", "samai": 2917, "g": 7351, "deri": 113.2}, {"m": 6, "d": 7, "kishu": "スマスロ 甲鉄城のカバネリ 海門決戦", "samai": 2687, "g": 6073, "deri": 114.7}, {"m": 6, "d": 7, "kishu": "スマスロ北斗の拳 転生の章2", "samai": 1905, "g": 6345, "deri": 110.0}, {"m": 6, "d": 7, "kishu": "Lパチスロからくりサーカス", "samai": 1780, "g": 4108, "deri": 114.4}, {"m": 6, "d": 7, "kishu": "Lスマスロ北斗の拳", "samai": 1686, "g": 6104, "deri": 109.2}, {"m": 6, "d": 7, "kishu": "スマスロ ゴッドイーター リザレクション", "samai": 1144, "g": 2726, "deri": 114.0}, {"m": 6, "d": 7, "kishu": "Lパチスロ かぐや様は告らせたい", "samai": 1129, "g": 4720, "deri": 108.0}, {"m": 6, "d": 7, "kishu": "スマスロ モンスターハンターライズ", "samai": 856, "g": 2980, "deri": 109.6}, {"m": 6, "d": 7, "kishu": "A-SLOT+異世界かるてっとBT", "samai": 837, "g": 4069, "deri": 106.9}, {"m": 6, "d": 7, "kishu": "Lタクトオーパス デスティニー", "samai": 780, "g": 6364, "deri": 104.1}, {"m": 6, "d": 7, "kishu": "LBスロットGALFY", "samai": 655, "g": 4000, "deri": 105.5}, {"m": 6, "d": 7, "kishu": "スマスロ化物語", "samai": 592, "g": 5918, "deri": 103.3}, {"m": 6, "d": 7, "kishu": "スロット ゾンビランドサガ", "samai": 560, "g": 802, "deri": 123.3}, {"m": 6, "d": 7, "kishu": "A-SLOT+ ディスクアップ ULTRAREMIX", "samai": 504, "g": 4545, "deri": 103.7}, {"m": 6, "d": 7, "kishu": "マイジャグラーV", "samai": 395, "g": 7026, "deri": 101.9}, {"m": 6, "d": 7, "kishu": "Lパチスロ革命機ヴァルヴレイヴ2", "samai": 392, "g": 7181, "deri": 101.8}, {"m": 6, "d": 7, "kishu": "スマスロモンキーターンV", "samai": 377, "g": 5279, "deri": 102.4}, {"m": 6, "d": 7, "kishu": "L東京喰種", "samai": 340, "g": 5641, "deri": 102.0}, {"m": 6, "d": 7, "kishu": "Lパチスロ炎炎ノ消防隊2", "samai": 318, "g": 5880, "deri": 101.8}, {"m": 6, "d": 7, "kishu": "L無職転生～異世界行ったら本気だす～", "samai": 305, "g": 4547, "deri": 102.2}, {"m": 6, "d": 7, "kishu": "スマスロ 東京リベンジャーズ", "samai": 268, "g": 3697, "deri": 102.4}, {"m": 6, "d": 7, "kishu": "ネオアイムジャグラーEX", "samai": 252, "g": 5609, "deri": 101.5}, {"m": 6, "d": 7, "kishu": "ハッピージャグラーＶＩＩＩ", "samai": 148, "g": 5542, "deri": 100.9}, {"m": 6, "d": 7, "kishu": "ゴーゴージャグラー３", "samai": 139, "g": 4811, "deri": 101.0}, {"m": 6, "d": 7, "kishu": "スマスロ バイオハザードRE:3", "samai": 87, "g": 2629, "deri": 101.1}, {"m": 6, "d": 7, "kishu": "ファンキージャグラー２ＫＴ", "samai": 34, "g": 5152, "deri": 100.2}, {"m": 6, "d": 7, "kishu": "もっと！クレアの秘宝伝　女神の歌声と太陽の子供達", "samai": -150, "g": 280, "deri": 79.4}, {"m": 6, "d": 7, "kishu": "ジャグラーガールズSS", "samai": -200, "g": 3119, "deri": 97.8}, {"m": 6, "d": 7, "kishu": "ウルトラミラクルジャグラー", "samai": -200, "g": 3469, "deri": 97.7}, {"m": 6, "d": 7, "kishu": "アレックス ブライト", "samai": -250, "g": 1466, "deri": 89.5}, {"m": 6, "d": 7, "kishu": "スマスロ サンダーV", "samai": -500, "g": 2133, "deri": 92.1}, {"m": 6, "d": 7, "kishu": "パチスロひぐらしのなく頃に祭２", "samai": -500, "g": 3584, "deri": 94.6}, {"m": 6, "d": 7, "kishu": "スマスロ 攻殻機動隊", "samai": -500, "g": 4357, "deri": 94.6}, {"m": 6, "d": 7, "kishu": "SHAKE BONUS TRIGGER", "samai": -500, "g": 3401, "deri": 93.0}, {"m": 6, "d": 7, "kishu": "スマスロ鉄拳6", "samai": -750, "g": 1117, "deri": 77.5}, {"m": 6, "d": 7, "kishu": "新ハナビ", "samai": -750, "g": 3289, "deri": 91.8}, {"m": 6, "d": 7, "kishu": "スマスロ マギアレコード 魔法少女まどか☆マギカ外伝", "samai": -750, "g": 2118, "deri": 85.7}, {"m": 6, "d": 7, "kishu": "スマスロヨルムンガンド", "samai": -1000, "g": 1254, "deri": 68.6}, {"m": 6, "d": 7, "kishu": "スマスロ ミリオンゴッド-神々の軌跡-", "samai": -1000, "g": 6893, "deri": 94.2}, {"m": 6, "d": 7, "kishu": "Lパチスロうみねこのなく頃に2", "samai": -1250, "g": 3928, "deri": 88.3}, {"m": 6, "d": 7, "kishu": "Lパチスロ 機動戦士ガンダムユニコーン 覚醒DRIVE", "samai": -1250, "g": 1560, "deri": 69.8}, {"m": 6, "d": 7, "kishu": "スマスロ スーパーリオエース2", "samai": -1500, "g": 6005, "deri": 91.3}, {"m": 6, "d": 7, "kishu": "L虚構推理", "samai": -2000, "g": 3199, "deri": 77.5}, {"m": 6, "d": 7, "kishu": "L ToLOVEるダークネス TRANCE ver.8.7", "samai": -2500, "g": 4486, "deri": 80.0}, {"m": 6, "d": 7, "kishu": "プリズムナナ", "samai": -2750, "g": 4234, "deri": 76.7}, {"m": 6, "d": 7, "kishu": "0", "samai": 289, "g": 4291, "deri": 102.2}, {"m": 6, "d": 7, "kishu": "1", "samai": 1408, "g": 5165, "deri": 109.1}, {"m": 6, "d": 7, "kishu": "3", "samai": 489, "g": 4988, "deri": 103.3}, {"m": 6, "d": 7, "kishu": "4", "samai": 57, "g": 4830, "deri": 100.4}, {"m": 6, "d": 7, "kishu": "5", "samai": 120, "g": 5249, "deri": 100.8}, {"m": 6, "d": 7, "kishu": "8", "samai": 554, "g": 4751, "deri": 103.9}, {"m": 6, "d": 7, "kishu": "9", "samai": 32, "g": 4549, "deri": 100.2}, {"m": 6, "d": 6, "kishu": "スマスロバジリスク～甲賀忍法帖～絆2 天膳 BLACK EDITION", "samai": 2677, "g": 7109, "deri": 112.6}, {"m": 6, "d": 6, "kishu": "スマスロ 東京リベンジャーズ", "samai": 2497, "g": 7010, "deri": 111.9}, {"m": 6, "d": 6, "kishu": "ハッピージャグラーＶＩＩＩ", "samai": 2355, "g": 7885, "deri": 110.0}, {"m": 6, "d": 6, "kishu": "Lスマスロ北斗の拳", "samai": 2198, "g": 5796, "deri": 112.6}, {"m": 6, "d": 6, "kishu": "スマスロ モンスターハンターライズ", "samai": 1682, "g": 7660, "deri": 107.3}, {"m": 6, "d": 6, "kishu": "スマスロ北斗の拳 転生の章2", "samai": 1672, "g": 6681, "deri": 108.3}, {"m": 6, "d": 6, "kishu": "Lパチスロ革命機ヴァルヴレイヴ2", "samai": 1333, "g": 7982, "deri": 105.6}, {"m": 6, "d": 6, "kishu": "スマスロ 甲鉄城のカバネリ 海門決戦", "samai": 1268, "g": 6426, "deri": 106.6}, {"m": 6, "d": 6, "kishu": "Lパチスロ かぐや様は告らせたい", "samai": 956, "g": 6542, "deri": 104.9}, {"m": 6, "d": 6, "kishu": "新ハナビ", "samai": 747, "g": 6405, "deri": 103.9}, {"m": 6, "d": 6, "kishu": "パチスロひぐらしのなく頃に祭２", "samai": 570, "g": 4565, "deri": 104.2}, {"m": 6, "d": 6, "kishu": "ファンキージャグラー２ＫＴ", "samai": 360, "g": 6740, "deri": 101.8}, {"m": 6, "d": 6, "kishu": "ジャグラーガールズSS", "samai": 360, "g": 6257, "deri": 101.9}, {"m": 6, "d": 6, "kishu": "ゴーゴージャグラー３", "samai": 307, "g": 6424, "deri": 101.6}, {"m": 6, "d": 6, "kishu": "マイジャグラーV", "samai": 285, "g": 7253, "deri": 101.3}, {"m": 6, "d": 6, "kishu": "スマスロ バイオハザードRE:3", "samai": 278, "g": 5617, "deri": 101.6}, {"m": 6, "d": 6, "kishu": "L東京喰種", "samai": 168, "g": 7073, "deri": 100.8}, {"m": 6, "d": 6, "kishu": "スロット ゾンビランドサガ", "samai": 113, "g": 6840, "deri": 100.6}, {"m": 6, "d": 6, "kishu": "スマスロ マギアレコード 魔法少女まどか☆マギカ外伝", "samai": 51, "g": 6277, "deri": 100.3}, {"m": 6, "d": 6, "kishu": "Lパチスロうみねこのなく頃に2", "samai": -100, "g": 6608, "deri": 99.3}, {"m": 6, "d": 6, "kishu": "ネオアイムジャグラーEX", "samai": -100, "g": 6108, "deri": 99.2}, {"m": 6, "d": 6, "kishu": "L虚構推理", "samai": -200, "g": 6382, "deri": 99.0}, {"m": 6, "d": 6, "kishu": "もっと！クレアの秘宝伝　女神の歌声と太陽の子供達", "samai": -200, "g": 4295, "deri": 98.3}, {"m": 6, "d": 6, "kishu": "スマスロモンキーターンV", "samai": -200, "g": 6236, "deri": 98.8}, {"m": 6, "d": 6, "kishu": "Lパチスロからくりサーカス", "samai": -200, "g": 5166, "deri": 98.6}, {"m": 6, "d": 6, "kishu": "アレックス ブライト", "samai": -250, "g": 3200, "deri": 97.2}, {"m": 6, "d": 6, "kishu": "スマスロ鉄拳6", "samai": -500, "g": 5953, "deri": 97.0}, {"m": 6, "d": 6, "kishu": "Lパチスロ 機動戦士ガンダムユニコーン 覚醒DRIVE", "samai": -500, "g": 5273, "deri": 96.4}, {"m": 6, "d": 6, "kishu": "A-SLOT+異世界かるてっとBT", "samai": -500, "g": 5801, "deri": 96.5}, {"m": 6, "d": 6, "kishu": "ウルトラミラクルジャグラー", "samai": -500, "g": 5939, "deri": 96.1}, {"m": 6, "d": 6, "kishu": "スマスロ サンダーV", "samai": -500, "g": 3640, "deri": 93.4}, {"m": 6, "d": 6, "kishu": "A-SLOT+ ディスクアップ ULTRAREMIX", "samai": -750, "g": 6312, "deri": 96.0}, {"m": 6, "d": 6, "kishu": "スマスロ スーパーリオエース2", "samai": -750, "g": 6560, "deri": 95.9}, {"m": 6, "d": 6, "kishu": "LBスロットGALFY", "samai": -750, "g": 4016, "deri": 93.0}, {"m": 6, "d": 6, "kishu": "スマスロ ミリオンゴッド-神々の軌跡-", "samai": -1000, "g": 7514, "deri": 95.0}, {"m": 6, "d": 6, "kishu": "Lパチスロ炎炎ノ消防隊2", "samai": -1250, "g": 6829, "deri": 93.9}, {"m": 6, "d": 6, "kishu": "SHAKE BONUS TRIGGER", "samai": -1250, "g": 5527, "deri": 92.4}, {"m": 6, "d": 6, "kishu": "スマスロ 攻殻機動隊", "samai": -1250, "g": 6254, "deri": 92.3}, {"m": 6, "d": 6, "kishu": "スマスロ化物語", "samai": -1500, "g": 6278, "deri": 91.8}, {"m": 6, "d": 6, "kishu": "スマスロ ゴッドイーター リザレクション", "samai": -1500, "g": 4434, "deri": 87.0}, {"m": 6, "d": 6, "kishu": "L ToLOVEるダークネス TRANCE ver.8.7", "samai": -2000, "g": 6526, "deri": 89.2}, {"m": 6, "d": 6, "kishu": "Lタクトオーパス デスティニー", "samai": -2250, "g": 7589, "deri": 90.1}, {"m": 6, "d": 6, "kishu": "L無職転生～異世界行ったら本気だす～", "samai": -2750, "g": 7117, "deri": 87.1}, {"m": 6, "d": 6, "kishu": "スマスロヨルムンガンド", "samai": -3250, "g": 4246, "deri": 74.4}, {"m": 6, "d": 6, "kishu": "プリズムナナ", "samai": -4750, "g": 6451, "deri": 74.8}, {"m": 6, "d": 6, "kishu": "4", "samai": 512, "g": 6125, "deri": 102.8}, {"m": 6, "d": 6, "kishu": "6", "samai": 1221, "g": 6900, "deri": 105.9}, {"m": 6, "d": 6, "kishu": "8", "samai": 191, "g": 6270, "deri": 101.0}, {"m": 6, "d": 5, "kishu": "L ToLOVEるダークネス TRANCE ver.8.7", "samai": 2095, "g": 3164, "deri": 122.1}, {"m": 6, "d": 5, "kishu": "新ハナビ", "samai": 1533, "g": 4036, "deri": 112.7}, {"m": 6, "d": 5, "kishu": "Lタクトオーパス デスティニー", "samai": 1365, "g": 6461, "deri": 107.0}, {"m": 6, "d": 5, "kishu": "SHAKE BONUS TRIGGER", "samai": 1273, "g": 5419, "deri": 107.8}, {"m": 6, "d": 5, "kishu": "Lパチスロ 機動戦士ガンダムユニコーン 覚醒DRIVE", "samai": 1233, "g": 1027, "deri": 140.0}, {"m": 6, "d": 5, "kishu": "スマスロ バイオハザードRE:3", "samai": 881, "g": 1755, "deri": 116.7}, {"m": 6, "d": 5, "kishu": "L虚構推理", "samai": 783, "g": 3277, "deri": 108.0}, {"m": 6, "d": 5, "kishu": "ハッピージャグラーＶＩＩＩ", "samai": 600, "g": 4901, "deri": 104.1}, {"m": 6, "d": 5, "kishu": "Lパチスロ革命機ヴァルヴレイヴ2", "samai": 558, "g": 7592, "deri": 102.5}, {"m": 6, "d": 5, "kishu": "Lパチスロからくりサーカス", "samai": 250, "g": 779, "deri": 110.7}, {"m": 6, "d": 5, "kishu": "スマスロ 東京リベンジャーズ", "samai": 197, "g": 984, "deri": 106.7}, {"m": 6, "d": 5, "kishu": "スマスロ 攻殻機動隊", "samai": 194, "g": 1737, "deri": 103.7}, {"m": 6, "d": 5, "kishu": "L東京喰種", "samai": 193, "g": 3381, "deri": 101.9}, {"m": 6, "d": 5, "kishu": "スマスロ 甲鉄城のカバネリ 海門決戦", "samai": 191, "g": 4710, "deri": 101.4}, {"m": 6, "d": 5, "kishu": "ウルトラミラクルジャグラー", "samai": 154, "g": 4934, "deri": 101.0}, {"m": 6, "d": 5, "kishu": "Lパチスロ かぐや様は告らせたい", "samai": 150, "g": 867, "deri": 105.8}, {"m": 6, "d": 5, "kishu": "スマスロ化物語", "samai": 130, "g": 2462, "deri": 101.8}, {"m": 6, "d": 5, "kishu": "スマスロヨルムンガンド", "samai": 103, "g": 1671, "deri": 102.0}, {"m": 6, "d": 5, "kishu": "Lパチスロ炎炎ノ消防隊2", "samai": 80, "g": 2326, "deri": 101.1}, {"m": 6, "d": 5, "kishu": "スマスロ ミリオンゴッド-神々の軌跡-", "samai": 48, "g": 5164, "deri": 100.3}, {"m": 6, "d": 5, "kishu": "マイジャグラーV", "samai": 46, "g": 5808, "deri": 100.3}, {"m": 6, "d": 5, "kishu": "スマスロモンキーターンV", "samai": -6, "g": 4107, "deri": 100.0}, {"m": 6, "d": 5, "kishu": "スマスロ マギアレコード 魔法少女まどか☆マギカ外伝", "samai": -41, "g": 914, "deri": 98.5}, {"m": 6, "d": 5, "kishu": "Lパチスロうみねこのなく頃に2", "samai": -87, "g": 3111, "deri": 99.1}, {"m": 6, "d": 5, "kishu": "L無職転生～異世界行ったら本気だす～", "samai": -100, "g": 1210, "deri": 96.0}, {"m": 6, "d": 5, "kishu": "もっと！クレアの秘宝伝　女神の歌声と太陽の子供達", "samai": -100, "g": 1033, "deri": 95.3}, {"m": 6, "d": 5, "kishu": "A-SLOT+異世界かるてっとBT", "samai": -150, "g": 1767, "deri": 97.2}, {"m": 6, "d": 5, "kishu": "A-SLOT+ ディスクアップ ULTRAREMIX", "samai": -150, "g": 2983, "deri": 98.3}, {"m": 6, "d": 5, "kishu": "スロット ゾンビランドサガ", "samai": -150, "g": 211, "deri": 74.8}, {"m": 6, "d": 5, "kishu": "スマスロ鉄拳6", "samai": -250, "g": 1183, "deri": 92.5}, {"m": 6, "d": 5, "kishu": "アレックス ブライト", "samai": -250, "g": 835, "deri": 88.8}, {"m": 6, "d": 5, "kishu": "ファンキージャグラー２ＫＴ", "samai": -250, "g": 4302, "deri": 97.8}, {"m": 6, "d": 5, "kishu": "スマスロ サンダーV", "samai": -250, "g": 1529, "deri": 93.5}, {"m": 6, "d": 5, "kishu": "Lスマスロ北斗の拳", "samai": -250, "g": 1566, "deri": 92.9}, {"m": 6, "d": 5, "kishu": "パチスロひぐらしのなく頃に祭２", "samai": -250, "g": 2267, "deri": 95.0}, {"m": 6, "d": 5, "kishu": "スマスロバジリスク～甲賀忍法帖～絆2 天膳 BLACK EDITION", "samai": -250, "g": 2045, "deri": 93.5}, {"m": 6, "d": 5, "kishu": "スマスロ モンスターハンターライズ", "samai": -250, "g": 1846, "deri": 92.0}, {"m": 6, "d": 5, "kishu": "スマスロ北斗の拳 転生の章2", "samai": -250, "g": 2018, "deri": 92.4}, {"m": 6, "d": 5, "kishu": "スマスロ スーパーリオエース2", "samai": -250, "g": 2498, "deri": 93.4}, {"m": 6, "d": 5, "kishu": "LBスロットGALFY", "samai": -500, "g": 1257, "deri": 86.3}, {"m": 6, "d": 5, "kishu": "スマスロ ゴッドイーター リザレクション", "samai": -500, "g": 774, "deri": 75.7}, {"m": 6, "d": 5, "kishu": "ネオアイムジャグラーEX", "samai": -500, "g": 4680, "deri": 95.9}, {"m": 6, "d": 5, "kishu": "ゴーゴージャグラー３", "samai": -500, "g": 4032, "deri": 95.0}, {"m": 6, "d": 5, "kishu": "ジャグラーガールズSS", "samai": -500, "g": 3698, "deri": 94.5}, {"m": 6, "d": 5, "kishu": "プリズムナナ", "samai": -750, "g": 735, "deri": 61.9}, {"m": 6, "d": 5, "kishu": "1", "samai": 35, "g": 2935, "deri": 100.4}, {"m": 6, "d": 5, "kishu": "2", "samai": 584, "g": 3169, "deri": 106.1}, {"m": 6, "d": 5, "kishu": "5", "samai": 107, "g": 3545, "deri": 101.0}, {"m": 6, "d": 5, "kishu": "7", "samai": 54, "g": 3323, "deri": 100.5}, {"m": 6, "d": 5, "kishu": "9", "samai": 297, "g": 3731, "deri": 102.7}, {"m": 6, "d": 4, "kishu": "Lパチスロ炎炎ノ消防隊2", "samai": 2830, "g": 6321, "deri": 114.9}, {"m": 6, "d": 4, "kishu": "スマスロ 攻殻機動隊", "samai": 1900, "g": 4007, "deri": 115.8}, {"m": 6, "d": 4, "kishu": "スマスロ スーパーリオエース2", "samai": 1373, "g": 3447, "deri": 113.3}, {"m": 6, "d": 4, "kishu": "SHAKE BONUS TRIGGER", "samai": 1167, "g": 3594, "deri": 110.8}, {"m": 6, "d": 4, "kishu": "スマスロヨルムンガンド", "samai": 1060, "g": 1540, "deri": 122.9}, {"m": 6, "d": 4, "kishu": "スマスロ鉄拳6", "samai": 1025, "g": 1586, "deri": 121.5}, {"m": 6, "d": 4, "kishu": "スマスロ 東京リベンジャーズ", "samai": 972, "g": 5409, "deri": 106.0}, {"m": 6, "d": 4, "kishu": "新ハナビ", "samai": 797, "g": 6333, "deri": 104.2}, {"m": 6, "d": 4, "kishu": "スマスロ サンダーV", "samai": 633, "g": 3035, "deri": 107.0}, {"m": 6, "d": 4, "kishu": "ウルトラミラクルジャグラー", "samai": 554, "g": 3716, "deri": 105.0}, {"m": 6, "d": 4, "kishu": "スマスロ ゴッドイーター リザレクション", "samai": 486, "g": 5916, "deri": 102.7}, {"m": 6, "d": 4, "kishu": "Lパチスロ かぐや様は告らせたい", "samai": 476, "g": 2280, "deri": 107.0}, {"m": 6, "d": 4, "kishu": "スマスロモンキーターンV", "samai": 397, "g": 2310, "deri": 105.7}, {"m": 6, "d": 4, "kishu": "Lパチスロうみねこのなく頃に2", "samai": 337, "g": 3448, "deri": 103.3}, {"m": 6, "d": 4, "kishu": "L無職転生～異世界行ったら本気だす～", "samai": 290, "g": 4388, "deri": 102.2}, {"m": 6, "d": 4, "kishu": "もっと！クレアの秘宝伝　女神の歌声と太陽の子供達", "samai": 280, "g": 1701, "deri": 105.5}, {"m": 6, "d": 4, "kishu": "LBスロットGALFY", "samai": 185, "g": 4535, "deri": 101.4}, {"m": 6, "d": 4, "kishu": "ネオアイムジャグラーEX", "samai": 181, "g": 4358, "deri": 101.4}, {"m": 6, "d": 4, "kishu": "スマスロバジリスク～甲賀忍法帖～絆2 天膳 BLACK EDITION", "samai": 127, "g": 2036, "deri": 102.1}, {"m": 6, "d": 4, "kishu": "スマスロ マギアレコード 魔法少女まどか☆マギカ外伝", "samai": 104, "g": 2182, "deri": 101.6}, {"m": 6, "d": 4, "kishu": "マイジャグラーV", "samai": 43, "g": 5292, "deri": 100.3}, {"m": 6, "d": 4, "kishu": "ゴーゴージャグラー３", "samai": -10, "g": 3995, "deri": 99.9}, {"m": 6, "d": 4, "kishu": "ジャグラーガールズSS", "samai": -20, "g": 4073, "deri": 99.8}, {"m": 6, "d": 4, "kishu": "スロット ゾンビランドサガ", "samai": -23, "g": 35, "deri": 77.6}, {"m": 6, "d": 4, "kishu": "L東京喰種", "samai": -81, "g": 3854, "deri": 99.3}, {"m": 6, "d": 4, "kishu": "ファンキージャグラー２ＫＴ", "samai": -100, "g": 4569, "deri": 99.1}, {"m": 6, "d": 4, "kishu": "パチスロひぐらしのなく頃に祭２", "samai": -150, "g": 1513, "deri": 96.1}, {"m": 6, "d": 4, "kishu": "アレックス ブライト", "samai": -200, "g": 1605, "deri": 95.6}, {"m": 6, "d": 4, "kishu": "Lパチスロからくりサーカス", "samai": -200, "g": 677, "deri": 88.6}, {"m": 6, "d": 4, "kishu": "Lパチスロ 機動戦士ガンダムユニコーン 覚醒DRIVE", "samai": -200, "g": 1810, "deri": 95.6}, {"m": 6, "d": 4, "kishu": "ハッピージャグラーＶＩＩＩ", "samai": -250, "g": 3349, "deri": 97.4}, {"m": 6, "d": 4, "kishu": "A-SLOT+ ディスクアップ ULTRAREMIX", "samai": -250, "g": 3237, "deri": 97.3}, {"m": 6, "d": 4, "kishu": "スマスロ北斗の拳 転生の章2", "samai": -250, "g": 1949, "deri": 94.6}, {"m": 6, "d": 4, "kishu": "スマスロ モンスターハンターライズ", "samai": -250, "g": 3384, "deri": 96.5}, {"m": 6, "d": 4, "kishu": "スマスロ 甲鉄城のカバネリ 海門決戦", "samai": -500, "g": 6102, "deri": 97.2}, {"m": 6, "d": 4, "kishu": "プリズムナナ", "samai": -500, "g": 1483, "deri": 86.5}, {"m": 6, "d": 4, "kishu": "Lパチスロ革命機ヴァルヴレイヴ2", "samai": -500, "g": 4125, "deri": 94.1}, {"m": 6, "d": 4, "kishu": "スマスロ ミリオンゴッド-神々の軌跡-", "samai": -500, "g": 6146, "deri": 96.0}, {"m": 6, "d": 4, "kishu": "スマスロ化物語", "samai": -750, "g": 3400, "deri": 91.8}, {"m": 6, "d": 4, "kishu": "スマスロ バイオハザードRE:3", "samai": -750, "g": 1526, "deri": 81.5}, {"m": 6, "d": 4, "kishu": "Lスマスロ北斗の拳", "samai": -750, "g": 3346, "deri": 91.0}, {"m": 6, "d": 4, "kishu": "A-SLOT+異世界かるてっとBT", "samai": -1000, "g": 2516, "deri": 85.2}, {"m": 6, "d": 4, "kishu": "L ToLOVEるダークネス TRANCE ver.8.7", "samai": -1500, "g": 2765, "deri": 81.6}, {"m": 6, "d": 4, "kishu": "L虚構推理", "samai": -2000, "g": 3128, "deri": 77.9}, {"m": 6, "d": 4, "kishu": "Lタクトオーパス デスティニー", "samai": -3750, "g": 4739, "deri": 72.9}, {"m": 6, "d": 4, "kishu": "1", "samai": 292, "g": 3223, "deri": 103.0}, {"m": 6, "d": 4, "kishu": "2", "samai": 573, "g": 3820, "deri": 105.0}, {"m": 6, "d": 4, "kishu": "4", "samai": 374, "g": 3569, "deri": 103.5}, {"m": 6, "d": 4, "kishu": "7", "samai": 235, "g": 3635, "deri": 102.2}, {"m": 6, "d": 4, "kishu": "8", "samai": 175, "g": 3792, "deri": 101.5}, {"m": 6, "d": 3, "kishu": "スマスロ モンスターハンターライズ", "samai": 3470, "g": 4403, "deri": 126.3}, {"m": 6, "d": 3, "kishu": "スマスロ 攻殻機動隊", "samai": 2382, "g": 5434, "deri": 114.6}, {"m": 6, "d": 3, "kishu": "L無職転生～異世界行ったら本気だす～", "samai": 1785, "g": 3677, "deri": 116.2}, {"m": 6, "d": 3, "kishu": "L東京喰種", "samai": 1358, "g": 6690, "deri": 106.8}, {"m": 6, "d": 3, "kishu": "スマスロ ミリオンゴッド-神々の軌跡-", "samai": 1278, "g": 8079, "deri": 105.3}, {"m": 6, "d": 3, "kishu": "L ToLOVEるダークネス TRANCE ver.8.7", "samai": 1035, "g": 4180, "deri": 108.3}, {"m": 6, "d": 3, "kishu": "Lスマスロ北斗の拳", "samai": 1010, "g": 3839, "deri": 108.8}, {"m": 6, "d": 3, "kishu": "L虚構推理", "samai": 717, "g": 5139, "deri": 104.6}, {"m": 6, "d": 3, "kishu": "Lパチスロ革命機ヴァルヴレイヴ2", "samai": 685, "g": 6455, "deri": 103.5}, {"m": 6, "d": 3, "kishu": "SHAKE BONUS TRIGGER", "samai": 600, "g": 2165, "deri": 109.2}, {"m": 6, "d": 3, "kishu": "アレックス ブライト", "samai": 430, "g": 1652, "deri": 108.7}, {"m": 6, "d": 3, "kishu": "スマスロ 甲鉄城のカバネリ 海門決戦", "samai": 400, "g": 6571, "deri": 102.0}, {"m": 6, "d": 3, "kishu": "スロット ゾンビランドサガ", "samai": 360, "g": 5014, "deri": 102.4}, {"m": 6, "d": 3, "kishu": "ファンキージャグラー２ＫＴ", "samai": 254, "g": 3495, "deri": 102.4}, {"m": 6, "d": 3, "kishu": "新ハナビ", "samai": 243, "g": 2214, "deri": 103.7}, {"m": 6, "d": 3, "kishu": "マイジャグラーV", "samai": 196, "g": 3891, "deri": 101.7}, {"m": 6, "d": 3, "kishu": "ジャグラーガールズSS", "samai": 175, "g": 2811, "deri": 102.1}, {"m": 6, "d": 3, "kishu": "ネオアイムジャグラーEX", "samai": 133, "g": 3364, "deri": 101.3}, {"m": 6, "d": 3, "kishu": "プリズムナナ", "samai": 105, "g": 501, "deri": 107.0}, {"m": 6, "d": 3, "kishu": "スマスロヨルムンガンド", "samai": -3, "g": 2954, "deri": 100.0}, {"m": 6, "d": 3, "kishu": "A-SLOT+ ディスクアップ ULTRAREMIX", "samai": -10, "g": 5209, "deri": 99.9}, {"m": 6, "d": 3, "kishu": "ゴーゴージャグラー３", "samai": -34, "g": 3726, "deri": 99.7}, {"m": 6, "d": 3, "kishu": "Lパチスロうみねこのなく頃に2", "samai": -73, "g": 2766, "deri": 99.1}, {"m": 6, "d": 3, "kishu": "スマスロバジリスク～甲賀忍法帖～絆2 天膳 BLACK EDITION", "samai": -100, "g": 2137, "deri": 98.3}, {"m": 6, "d": 3, "kishu": "スマスロ北斗の拳 転生の章2", "samai": -100, "g": 2908, "deri": 98.6}, {"m": 6, "d": 3, "kishu": "ハッピージャグラーＶＩＩＩ", "samai": -100, "g": 3609, "deri": 98.7}, {"m": 6, "d": 3, "kishu": "もっと！クレアの秘宝伝　女神の歌声と太陽の子供達", "samai": -200, "g": 684, "deri": 89.6}, {"m": 6, "d": 3, "kishu": "ウルトラミラクルジャグラー", "samai": -250, "g": 3070, "deri": 97.3}, {"m": 6, "d": 3, "kishu": "A-SLOT+異世界かるてっとBT", "samai": -250, "g": 2564, "deri": 96.7}, {"m": 6, "d": 3, "kishu": "パチスロひぐらしのなく頃に祭２", "samai": -250, "g": 2926, "deri": 95.3}, {"m": 6, "d": 3, "kishu": "スマスロ サンダーV", "samai": -250, "g": 3337, "deri": 95.8}, {"m": 6, "d": 3, "kishu": "Lパチスロ 機動戦士ガンダムユニコーン 覚醒DRIVE", "samai": -250, "g": 778, "deri": 79.6}, {"m": 6, "d": 3, "kishu": "スマスロ鉄拳6", "samai": -250, "g": 2194, "deri": 92.6}, {"m": 6, "d": 3, "kishu": "スマスロ ゴッドイーター リザレクション", "samai": -500, "g": 2903, "deri": 93.8}, {"m": 6, "d": 3, "kishu": "Lパチスロからくりサーカス", "samai": -500, "g": 1966, "deri": 90.0}, {"m": 6, "d": 3, "kishu": "スマスロ マギアレコード 魔法少女まどか☆マギカ外伝", "samai": -500, "g": 3757, "deri": 93.8}, {"m": 6, "d": 3, "kishu": "スマスロモンキーターンV", "samai": -500, "g": 3023, "deri": 92.0}, {"m": 6, "d": 3, "kishu": "スマスロ 東京リベンジャーズ", "samai": -750, "g": 2348, "deri": 88.5}, {"m": 6, "d": 3, "kishu": "Lタクトオーパス デスティニー", "samai": -750, "g": 6819, "deri": 95.5}, {"m": 6, "d": 3, "kishu": "Lパチスロ かぐや様は告らせたい", "samai": -750, "g": 2872, "deri": 88.5}, {"m": 6, "d": 3, "kishu": "Lパチスロ炎炎ノ消防隊2", "samai": -1000, "g": 4575, "deri": 91.0}, {"m": 6, "d": 3, "kishu": "LBスロットGALFY", "samai": -1000, "g": 2340, "deri": 82.4}, {"m": 6, "d": 3, "kishu": "スマスロ スーパーリオエース2", "samai": -1250, "g": 5590, "deri": 91.2}, {"m": 6, "d": 3, "kishu": "スマスロ化物語", "samai": -1750, "g": 6296, "deri": 90.2}, {"m": 6, "d": 3, "kishu": "スマスロ バイオハザードRE:3", "samai": -2250, "g": 5777, "deri": 85.7}, {"m": 6, "d": 3, "kishu": "0", "samai": 482, "g": 4190, "deri": 103.8}, {"m": 6, "d": 3, "kishu": "3", "samai": 344, "g": 4119, "deri": 102.8}, {"m": 6, "d": 3, "kishu": "4", "samai": 158, "g": 3894, "deri": 101.4}, {"m": 6, "d": 3, "kishu": "5", "samai": 383, "g": 3856, "deri": 103.3}, {"m": 6, "d": 3, "kishu": "6", "samai": 325, "g": 4823, "deri": 102.2}, {"m": 6, "d": 3, "kishu": "9", "samai": 675, "g": 4211, "deri": 105.3}, {"m": 6, "d": 2, "kishu": "L ToLOVEるダークネス TRANCE ver.8.7", "samai": 2948, "g": 2101, "deri": 146.8}, {"m": 6, "d": 2, "kishu": "Lパチスロ革命機ヴァルヴレイヴ2", "samai": 1733, "g": 4986, "deri": 111.6}, {"m": 6, "d": 2, "kishu": "スマスロバジリスク～甲賀忍法帖～絆2 天膳 BLACK EDITION", "samai": 1640, "g": 2411, "deri": 122.7}, {"m": 6, "d": 2, "kishu": "LBスロットGALFY", "samai": 715, "g": 1609, "deri": 114.8}, {"m": 6, "d": 2, "kishu": "A-SLOT+異世界かるてっとBT", "samai": 670, "g": 2629, "deri": 108.5}, {"m": 6, "d": 2, "kishu": "A-SLOT+ ディスクアップ ULTRAREMIX", "samai": 414, "g": 2571, "deri": 105.4}, {"m": 6, "d": 2, "kishu": "スマスロ バイオハザードRE:3", "samai": 376, "g": 2212, "deri": 105.7}, {"m": 6, "d": 2, "kishu": "L虚構推理", "samai": 363, "g": 2623, "deri": 104.6}, {"m": 6, "d": 2, "kishu": "ウルトラミラクルジャグラー", "samai": 249, "g": 3336, "deri": 102.5}, {"m": 6, "d": 2, "kishu": "スマスロ 甲鉄城のカバネリ 海門決戦", "samai": 178, "g": 5572, "deri": 101.1}, {"m": 6, "d": 2, "kishu": "マイジャグラーV", "samai": 177, "g": 4268, "deri": 101.4}, {"m": 6, "d": 2, "kishu": "スマスロヨルムンガンド", "samai": 158, "g": 1666, "deri": 103.2}, {"m": 6, "d": 2, "kishu": "Lスマスロ北斗の拳", "samai": 102, "g": 737, "deri": 104.6}, {"m": 6, "d": 2, "kishu": "Lパチスロうみねこのなく頃に2", "samai": 100, "g": 2563, "deri": 101.3}, {"m": 6, "d": 2, "kishu": "スマスロ鉄拳6", "samai": 73, "g": 1237, "deri": 102.0}, {"m": 6, "d": 2, "kishu": "スマスロモンキーターンV", "samai": 71, "g": 1649, "deri": 101.4}, {"m": 6, "d": 2, "kishu": "Lパチスロ かぐや様は告らせたい", "samai": 0, "g": 780, "deri": 100.0}, {"m": 6, "d": 2, "kishu": "新ハナビ", "samai": -73, "g": 1883, "deri": 98.7}, {"m": 6, "d": 2, "kishu": "もっと！クレアの秘宝伝　女神の歌声と太陽の子供達", "samai": -77, "g": 165, "deri": 84.5}, {"m": 6, "d": 2, "kishu": "スマスロ ゴッドイーター リザレクション", "samai": -100, "g": 1202, "deri": 97.2}, {"m": 6, "d": 2, "kishu": "Lパチスロからくりサーカス", "samai": -150, "g": 400, "deri": 86.9}, {"m": 6, "d": 2, "kishu": "ネオアイムジャグラーEX", "samai": -150, "g": 3428, "deri": 98.2}, {"m": 6, "d": 2, "kishu": "ゴーゴージャグラー３", "samai": -200, "g": 3361, "deri": 97.9}, {"m": 6, "d": 2, "kishu": "L東京喰種", "samai": -250, "g": 3669, "deri": 97.6}, {"m": 6, "d": 2, "kishu": "ファンキージャグラー２ＫＴ", "samai": -250, "g": 3976, "deri": 97.6}, {"m": 6, "d": 2, "kishu": "スマスロ北斗の拳 転生の章2", "samai": -250, "g": 2526, "deri": 95.9}, {"m": 6, "d": 2, "kishu": "スマスロ マギアレコード 魔法少女まどか☆マギカ外伝", "samai": -250, "g": 1103, "deri": 90.2}, {"m": 6, "d": 2, "kishu": "スマスロ スーパーリオエース2", "samai": -250, "g": 2474, "deri": 95.5}, {"m": 6, "d": 2, "kishu": "スマスロ ミリオンゴッド-神々の軌跡-", "samai": -250, "g": 3982, "deri": 97.0}, {"m": 6, "d": 2, "kishu": "ジャグラーガールズSS", "samai": -250, "g": 2679, "deri": 95.2}, {"m": 6, "d": 2, "kishu": "パチスロひぐらしのなく頃に祭２", "samai": -250, "g": 3709, "deri": 96.3}, {"m": 6, "d": 2, "kishu": "スマスロ モンスターハンターライズ", "samai": -250, "g": 1271, "deri": 88.9}, {"m": 6, "d": 2, "kishu": "Lパチスロ炎炎ノ消防隊2", "samai": -250, "g": 1974, "deri": 92.7}, {"m": 6, "d": 2, "kishu": "アレックス ブライト", "samai": -250, "g": 1282, "deri": 88.0}, {"m": 6, "d": 2, "kishu": "スマスロ サンダーV", "samai": -500, "g": 924, "deri": 79.4}, {"m": 6, "d": 2, "kishu": "Lパチスロ 機動戦士ガンダムユニコーン 覚醒DRIVE", "samai": -500, "g": 822, "deri": 75.3}, {"m": 6, "d": 2, "kishu": "スマスロ 東京リベンジャーズ", "samai": -500, "g": 1746, "deri": 88.1}, {"m": 6, "d": 2, "kishu": "ハッピージャグラーＶＩＩＩ", "samai": -750, "g": 2228, "deri": 88.5}, {"m": 6, "d": 2, "kishu": "プリズムナナ", "samai": -750, "g": 1260, "deri": 74.1}, {"m": 6, "d": 2, "kishu": "SHAKE BONUS TRIGGER", "samai": -1000, "g": 1505, "deri": 76.7}, {"m": 6, "d": 2, "kishu": "スマスロ 攻殻機動隊", "samai": -1000, "g": 1242, "deri": 70.3}, {"m": 6, "d": 2, "kishu": "スロット ゾンビランドサガ", "samai": -1000, "g": 1543, "deri": 73.6}, {"m": 6, "d": 2, "kishu": "スマスロ化物語", "samai": -1000, "g": 1572, "deri": 73.7}, {"m": 6, "d": 2, "kishu": "Lタクトオーパス デスティニー", "samai": -1250, "g": 4662, "deri": 90.5}, {"m": 6, "d": 2, "kishu": "L無職転生～異世界行ったら本気だす～", "samai": -1250, "g": 2242, "deri": 78.7}, {"m": 6, "d": 2, "kishu": "0", "samai": 409, "g": 3359, "deri": 104.1}, {"m": 6, "d": 2, "kishu": "1", "samai": 197, "g": 2598, "deri": 102.5}, {"m": 6, "d": 2, "kishu": "5", "samai": 251, "g": 2636, "deri": 103.2}, {"m": 6, "d": 2, "kishu": "6", "samai": 105, "g": 2646, "deri": 101.3}, {"m": 6, "d": 2, "kishu": "7", "samai": 382, "g": 2458, "deri": 105.2}, {"m": 6, "d": 2, "kishu": "8", "samai": 6, "g": 2561, "deri": 100.1}, {"m": 6, "d": 1, "kishu": "スマスロ 甲鉄城のカバネリ 海門決戦", "samai": 3014, "g": 6586, "deri": 115.3}, {"m": 6, "d": 1, "kishu": "Lパチスロ炎炎ノ消防隊2", "samai": 2894, "g": 7736, "deri": 112.5}, {"m": 6, "d": 1, "kishu": "スマスロ 攻殻機動隊", "samai": 2892, "g": 4365, "deri": 122.1}, {"m": 6, "d": 1, "kishu": "スマスロ 東京リベンジャーズ", "samai": 2568, "g": 7905, "deri": 110.8}, {"m": 6, "d": 1, "kishu": "プリズムナナ", "samai": 2015, "g": 3578, "deri": 118.8}, {"m": 6, "d": 1, "kishu": "スマスロ北斗の拳 転生の章2", "samai": 1535, "g": 4056, "deri": 112.6}, {"m": 6, "d": 1, "kishu": "L東京喰種", "samai": 1283, "g": 6281, "deri": 106.8}, {"m": 6, "d": 1, "kishu": "スマスロ モンスターハンターライズ", "samai": 1218, "g": 3798, "deri": 110.7}, {"m": 6, "d": 1, "kishu": "Lパチスロ革命機ヴァルヴレイヴ2", "samai": 1147, "g": 3801, "deri": 110.1}, {"m": 6, "d": 1, "kishu": "パチスロひぐらしのなく頃に祭２", "samai": 1120, "g": 2973, "deri": 112.6}, {"m": 6, "d": 1, "kishu": "スマスロ スーパーリオエース2", "samai": 1115, "g": 5236, "deri": 107.1}, {"m": 6, "d": 1, "kishu": "新ハナビ", "samai": 860, "g": 3891, "deri": 107.4}, {"m": 6, "d": 1, "kishu": "スマスロバジリスク～甲賀忍法帖～絆2 天膳 BLACK EDITION", "samai": 697, "g": 1833, "deri": 112.7}, {"m": 6, "d": 1, "kishu": "スマスロ化物語", "samai": 528, "g": 3076, "deri": 105.7}, {"m": 6, "d": 1, "kishu": "ウルトラミラクルジャグラー", "samai": 365, "g": 3945, "deri": 103.1}, {"m": 6, "d": 1, "kishu": "Lスマスロ北斗の拳", "samai": 290, "g": 2981, "deri": 103.2}, {"m": 6, "d": 1, "kishu": "ジャグラーガールズSS", "samai": 237, "g": 3591, "deri": 102.2}, {"m": 6, "d": 1, "kishu": "A-SLOT+ ディスクアップ ULTRAREMIX", "samai": 188, "g": 3586, "deri": 101.7}, {"m": 6, "d": 1, "kishu": "Lパチスロうみねこのなく頃に2", "samai": 123, "g": 4347, "deri": 100.9}, {"m": 6, "d": 1, "kishu": "ゴーゴージャグラー３", "samai": 44, "g": 4516, "deri": 100.3}, {"m": 6, "d": 1, "kishu": "スロット ゾンビランドサガ", "samai": 23, "g": 1778, "deri": 100.4}, {"m": 6, "d": 1, "kishu": "アレックス ブライト", "samai": 7, "g": 1778, "deri": 100.1}, {"m": 6, "d": 1, "kishu": "マイジャグラーV", "samai": -11, "g": 4516, "deri": 99.9}, {"m": 6, "d": 1, "kishu": "もっと！クレアの秘宝伝　女神の歌声と太陽の子供達", "samai": -13, "g": 13, "deri": 64.9}, {"m": 6, "d": 1, "kishu": "スマスロ マギアレコード 魔法少女まどか☆マギカ外伝", "samai": -16, "g": 2603, "deri": 99.8}, {"m": 6, "d": 1, "kishu": "SHAKE BONUS TRIGGER", "samai": -80, "g": 1548, "deri": 98.3}, {"m": 6, "d": 1, "kishu": "ハッピージャグラーＶＩＩＩ", "samai": -90, "g": 3503, "deri": 99.1}, {"m": 6, "d": 1, "kishu": "ネオアイムジャグラーEX", "samai": -100, "g": 3946, "deri": 99.0}, {"m": 6, "d": 1, "kishu": "スマスロ サンダーV", "samai": -100, "g": 1748, "deri": 97.7}, {"m": 6, "d": 1, "kishu": "スマスロモンキーターンV", "samai": -150, "g": 2677, "deri": 98.1}, {"m": 6, "d": 1, "kishu": "スマスロヨルムンガンド", "samai": -150, "g": 1492, "deri": 95.8}, {"m": 6, "d": 1, "kishu": "L虚構推理", "samai": -200, "g": 3262, "deri": 97.7}, {"m": 6, "d": 1, "kishu": "Lパチスロからくりサーカス", "samai": -250, "g": 1343, "deri": 93.4}, {"m": 6, "d": 1, "kishu": "Lパチスロ 機動戦士ガンダムユニコーン 覚醒DRIVE", "samai": -250, "g": 2182, "deri": 94.9}, {"m": 6, "d": 1, "kishu": "ファンキージャグラー２ＫＴ", "samai": -250, "g": 4049, "deri": 97.2}, {"m": 6, "d": 1, "kishu": "A-SLOT+異世界かるてっとBT", "samai": -250, "g": 3046, "deri": 95.8}, {"m": 6, "d": 1, "kishu": "スマスロ バイオハザードRE:3", "samai": -250, "g": 2976, "deri": 95.5}, {"m": 6, "d": 1, "kishu": "L無職転生～異世界行ったら本気だす～", "samai": -500, "g": 1245, "deri": 80.3}, {"m": 6, "d": 1, "kishu": "スマスロ鉄拳6", "samai": -1000, "g": 2905, "deri": 87.6}, {"m": 6, "d": 1, "kishu": "LBスロットGALFY", "samai": -1000, "g": 2908, "deri": 86.2}, {"m": 6, "d": 1, "kishu": "スマスロ ゴッドイーター リザレクション", "samai": -1250, "g": 3773, "deri": 88.7}, {"m": 6, "d": 1, "kishu": "Lパチスロ かぐや様は告らせたい", "samai": -1250, "g": 3446, "deri": 86.7}, {"m": 6, "d": 1, "kishu": "Lタクトオーパス デスティニー", "samai": -1500, "g": 4953, "deri": 89.1}, {"m": 6, "d": 1, "kishu": "スマスロ ミリオンゴッド-神々の軌跡-", "samai": -1500, "g": 4737, "deri": 88.2}, {"m": 6, "d": 1, "kishu": "L ToLOVEるダークネス TRANCE ver.8.7", "samai": -1750, "g": 4917, "deri": 87.1}, {"m": 6, "d": 1, "kishu": "0", "samai": 80, "g": 3945, "deri": 100.7}, {"m": 6, "d": 1, "kishu": "1", "samai": 965, "g": 4407, "deri": 107.3}, {"m": 6, "d": 1, "kishu": "2", "samai": 318, "g": 3800, "deri": 102.8}, {"m": 6, "d": 1, "kishu": "3", "samai": 381, "g": 4333, "deri": 102.9}, {"m": 6, "d": 1, "kishu": "5", "samai": 477, "g": 3367, "deri": 104.7}, {"m": 6, "d": 1, "kishu": "7", "samai": 293, "g": 3988, "deri": 102.5}, {"m": 6, "d": 1, "kishu": "8", "samai": 871, "g": 4209, "deri": 106.9}, {"m": 6, "d": 1, "kishu": "9", "samai": 139, "g": 3513, "deri": 101.3}, {"m": 5, "d": 31, "kishu": "プリズムナナ", "samai": 4775, "g": 6029, "deri": 126.4}, {"m": 5, "d": 31, "kishu": "Lパチスロ 機動戦士ガンダムユニコーン 覚醒DRIVE", "samai": 2543, "g": 4786, "deri": 117.7}, {"m": 5, "d": 31, "kishu": "スマスロ ミリオンゴッド-神々の軌跡-", "samai": 1954, "g": 7709, "deri": 108.4}, {"m": 5, "d": 31, "kishu": "Lパチスロ炎炎ノ消防隊2", "samai": 1842, "g": 6370, "deri": 109.6}, {"m": 5, "d": 31, "kishu": "スマスロ化物語", "samai": 1562, "g": 6942, "deri": 107.5}, {"m": 5, "d": 31, "kishu": "L無職転生～異世界行ったら本気だす～", "samai": 1070, "g": 4945, "deri": 107.2}, {"m": 5, "d": 31, "kishu": "ハッピージャグラーＶＩＩＩ", "samai": 863, "g": 5115, "deri": 105.6}, {"m": 5, "d": 31, "kishu": "スマスロ 東京リベンジャーズ", "samai": 827, "g": 6524, "deri": 104.2}, {"m": 5, "d": 31, "kishu": "スマスロ 甲鉄城のカバネリ 海門決戦", "samai": 817, "g": 5751, "deri": 104.7}, {"m": 5, "d": 31, "kishu": "スマスロモンキーターンV", "samai": 680, "g": 6386, "deri": 103.5}, {"m": 5, "d": 31, "kishu": "LBスロットGALFY", "samai": 470, "g": 5151, "deri": 103.0}, {"m": 5, "d": 31, "kishu": "スマスロ モンスターハンターライズ", "samai": 380, "g": 5229, "deri": 102.4}, {"m": 5, "d": 31, "kishu": "アレックス ブライト", "samai": 253, "g": 3639, "deri": 102.3}, {"m": 5, "d": 31, "kishu": "Lタクトオーパス デスティニー", "samai": 180, "g": 7367, "deri": 100.8}, {"m": 5, "d": 31, "kishu": "ゴーゴージャグラー３", "samai": 158, "g": 5828, "deri": 100.9}, {"m": 5, "d": 31, "kishu": "L東京喰種", "samai": 120, "g": 6983, "deri": 100.6}, {"m": 5, "d": 31, "kishu": "ネオアイムジャグラーEX", "samai": 29, "g": 6383, "deri": 100.2}, {"m": 5, "d": 31, "kishu": "もっと！クレアの秘宝伝　女神の歌声と太陽の子供達", "samai": 0, "g": 1195, "deri": 100.0}, {"m": 5, "d": 31, "kishu": "マイジャグラーV", "samai": -200, "g": 4974, "deri": 98.6}, {"m": 5, "d": 31, "kishu": "新ハナビ", "samai": -200, "g": 2342, "deri": 96.5}, {"m": 5, "d": 31, "kishu": "A-SLOT+ ディスクアップ ULTRAREMIX", "samai": -250, "g": 6021, "deri": 98.5}, {"m": 5, "d": 31, "kishu": "スマスロ サンダーV", "samai": -250, "g": 1972, "deri": 95.0}, {"m": 5, "d": 31, "kishu": "パチスロひぐらしのなく頃に祭２", "samai": -250, "g": 2130, "deri": 95.1}, {"m": 5, "d": 31, "kishu": "スマスロ スーパーリオエース2", "samai": -250, "g": 5491, "deri": 97.8}, {"m": 5, "d": 31, "kishu": "ウルトラミラクルジャグラー", "samai": -250, "g": 3366, "deri": 96.1}, {"m": 5, "d": 31, "kishu": "Lパチスロうみねこのなく頃に2", "samai": -250, "g": 4298, "deri": 96.6}, {"m": 5, "d": 31, "kishu": "ファンキージャグラー２ＫＴ", "samai": -250, "g": 4665, "deri": 96.8}, {"m": 5, "d": 31, "kishu": "L ToLOVEるダークネス TRANCE ver.8.7", "samai": -250, "g": 5420, "deri": 97.0}, {"m": 5, "d": 31, "kishu": "スマスロ ゴッドイーター リザレクション", "samai": -500, "g": 4591, "deri": 96.2}, {"m": 5, "d": 31, "kishu": "SHAKE BONUS TRIGGER", "samai": -500, "g": 3308, "deri": 94.6}, {"m": 5, "d": 31, "kishu": "A-SLOT+異世界かるてっとBT", "samai": -500, "g": 3626, "deri": 94.1}, {"m": 5, "d": 31, "kishu": "Lパチスロ革命機ヴァルヴレイヴ2", "samai": -500, "g": 7130, "deri": 96.7}, {"m": 5, "d": 31, "kishu": "スマスロ北斗の拳 転生の章2", "samai": -500, "g": 4946, "deri": 95.1}, {"m": 5, "d": 31, "kishu": "スマスロ鉄拳6", "samai": -500, "g": 3820, "deri": 93.6}, {"m": 5, "d": 31, "kishu": "スマスロ バイオハザードRE:3", "samai": -750, "g": 4714, "deri": 94.4}, {"m": 5, "d": 31, "kishu": "スマスロバジリスク～甲賀忍法帖～絆2 天膳 BLACK EDITION", "samai": -750, "g": 6801, "deri": 96.0}, {"m": 5, "d": 31, "kishu": "スマスロ マギアレコード 魔法少女まどか☆マギカ外伝", "samai": -750, "g": 4742, "deri": 94.2}, {"m": 5, "d": 31, "kishu": "スマスロヨルムンガンド", "samai": -750, "g": 4379, "deri": 93.0}, {"m": 5, "d": 31, "kishu": "スマスロ 攻殻機動隊", "samai": -750, "g": 5667, "deri": 94.6}, {"m": 5, "d": 31, "kishu": "ジャグラーガールズSS", "samai": -750, "g": 3795, "deri": 91.6}, {"m": 5, "d": 31, "kishu": "Lパチスロからくりサーカス", "samai": -1250, "g": 4735, "deri": 90.9}, {"m": 5, "d": 31, "kishu": "Lスマスロ北斗の拳", "samai": -1250, "g": 3246, "deri": 86.4}, {"m": 5, "d": 31, "kishu": "スロット ゾンビランドサガ", "samai": -1750, "g": 3115, "deri": 79.4}, {"m": 5, "d": 31, "kishu": "Lパチスロ かぐや様は告らせたい", "samai": -1750, "g": 5498, "deri": 87.9}, {"m": 5, "d": 31, "kishu": "L虚構推理", "samai": -2750, "g": 6820, "deri": 85.7}, {"m": 5, "d": 31, "kishu": "5", "samai": 348, "g": 5227, "deri": 102.2}, {"m": 5, "d": 31, "kishu": "6", "samai": 354, "g": 5589, "deri": 102.1}, {"m": 5, "d": 31, "kishu": "9", "samai": 36, "g": 5558, "deri": 100.2}, {"m": 5, "d": 30, "kishu": "スマスロ ミリオンゴッド-神々の軌跡-", "samai": 2979, "g": 7477, "deri": 113.3}, {"m": 5, "d": 30, "kishu": "スマスロ鉄拳6", "samai": 1488, "g": 3091, "deri": 116.1}, {"m": 5, "d": 30, "kishu": "Lパチスロ炎炎ノ消防隊2", "samai": 1382, "g": 4882, "deri": 109.4}, {"m": 5, "d": 30, "kishu": "スマスロ ゴッドイーター リザレクション", "samai": 1322, "g": 3592, "deri": 112.3}, {"m": 5, "d": 30, "kishu": "Lパチスロからくりサーカス", "samai": 1284, "g": 2510, "deri": 117.1}, {"m": 5, "d": 30, "kishu": "スマスロ マギアレコード 魔法少女まどか☆マギカ外伝", "samai": 1265, "g": 4392, "deri": 109.6}, {"m": 5, "d": 30, "kishu": "L虚構推理", "samai": 1237, "g": 6382, "deri": 106.5}, {"m": 5, "d": 30, "kishu": "スマスロモンキーターンV", "samai": 1196, "g": 5268, "deri": 107.6}, {"m": 5, "d": 30, "kishu": "ジャグラーガールズSS", "samai": 1140, "g": 5739, "deri": 106.6}, {"m": 5, "d": 30, "kishu": "SHAKE BONUS TRIGGER", "samai": 1083, "g": 4979, "deri": 107.3}, {"m": 5, "d": 30, "kishu": "L ToLOVEるダークネス TRANCE ver.8.7", "samai": 920, "g": 5064, "deri": 106.1}, {"m": 5, "d": 30, "kishu": "ネオアイムジャグラーEX", "samai": 572, "g": 6097, "deri": 103.1}, {"m": 5, "d": 30, "kishu": "スマスロヨルムンガンド", "samai": 558, "g": 3132, "deri": 105.9}, {"m": 5, "d": 30, "kishu": "スマスロ サンダーV", "samai": 537, "g": 3284, "deri": 105.4}, {"m": 5, "d": 30, "kishu": "Lパチスロうみねこのなく頃に2", "samai": 370, "g": 5732, "deri": 102.2}, {"m": 5, "d": 30, "kishu": "パチスロひぐらしのなく頃に祭２", "samai": 280, "g": 3056, "deri": 103.1}, {"m": 5, "d": 30, "kishu": "アレックス ブライト", "samai": 170, "g": 2647, "deri": 102.1}, {"m": 5, "d": 30, "kishu": "L東京喰種", "samai": 52, "g": 6673, "deri": 100.3}, {"m": 5, "d": 30, "kishu": "スマスロ モンスターハンターライズ", "samai": 28, "g": 2752, "deri": 100.3}, {"m": 5, "d": 30, "kishu": "ウルトラミラクルジャグラー", "samai": 26, "g": 4397, "deri": 100.2}, {"m": 5, "d": 30, "kishu": "Lパチスロ 機動戦士ガンダムユニコーン 覚醒DRIVE", "samai": 0, "g": 2274, "deri": 100.0}, {"m": 5, "d": 30, "kishu": "ゴーゴージャグラー３", "samai": -100, "g": 5418, "deri": 99.3}, {"m": 5, "d": 30, "kishu": "スマスロ北斗の拳 転生の章2", "samai": -100, "g": 3749, "deri": 98.7}, {"m": 5, "d": 30, "kishu": "A-SLOT+ ディスクアップ ULTRAREMIX", "samai": -200, "g": 6227, "deri": 98.7}, {"m": 5, "d": 30, "kishu": "もっと！クレアの秘宝伝　女神の歌声と太陽の子供達", "samai": -250, "g": 593, "deri": 81.6}, {"m": 5, "d": 30, "kishu": "マイジャグラーV", "samai": -250, "g": 6010, "deri": 97.7}, {"m": 5, "d": 30, "kishu": "新ハナビ", "samai": -250, "g": 4710, "deri": 96.7}, {"m": 5, "d": 30, "kishu": "スマスロ スーパーリオエース2", "samai": -500, "g": 5388, "deri": 96.8}, {"m": 5, "d": 30, "kishu": "Lスマスロ北斗の拳", "samai": -500, "g": 3559, "deri": 95.0}, {"m": 5, "d": 30, "kishu": "A-SLOT+異世界かるてっとBT", "samai": -500, "g": 2587, "deri": 92.9}, {"m": 5, "d": 30, "kishu": "ファンキージャグラー２ＫＴ", "samai": -500, "g": 4152, "deri": 95.5}, {"m": 5, "d": 30, "kishu": "ハッピージャグラーＶＩＩＩ", "samai": -500, "g": 4245, "deri": 95.2}, {"m": 5, "d": 30, "kishu": "スロット ゾンビランドサガ", "samai": -750, "g": 2595, "deri": 89.9}, {"m": 5, "d": 30, "kishu": "スマスロバジリスク～甲賀忍法帖～絆2 天膳 BLACK EDITION", "samai": -750, "g": 1047, "deri": 73.4}, {"m": 5, "d": 30, "kishu": "スマスロ 甲鉄城のカバネリ 海門決戦", "samai": -750, "g": 5642, "deri": 94.8}, {"m": 5, "d": 30, "kishu": "Lパチスロ かぐや様は告らせたい", "samai": -750, "g": 6086, "deri": 95.0}, {"m": 5, "d": 30, "kishu": "スマスロ 東京リベンジャーズ", "samai": -750, "g": 2631, "deri": 87.7}, {"m": 5, "d": 30, "kishu": "プリズムナナ", "samai": -1000, "g": 2882, "deri": 87.6}, {"m": 5, "d": 30, "kishu": "Lパチスロ革命機ヴァルヴレイヴ2", "samai": -1250, "g": 7230, "deri": 93.2}, {"m": 5, "d": 30, "kishu": "Lタクトオーパス デスティニー", "samai": -1500, "g": 6863, "deri": 91.8}, {"m": 5, "d": 30, "kishu": "L無職転生～異世界行ったら本気だす～", "samai": -2000, "g": 2101, "deri": 68.2}, {"m": 5, "d": 30, "kishu": "スマスロ バイオハザードRE:3", "samai": -2000, "g": 3084, "deri": 78.2}, {"m": 5, "d": 30, "kishu": "スマスロ化物語", "samai": -2000, "g": 4617, "deri": 85.4}, {"m": 5, "d": 30, "kishu": "LBスロットGALFY", "samai": -2250, "g": 5410, "deri": 84.7}, {"m": 5, "d": 30, "kishu": "スマスロ 攻殻機動隊", "samai": -2500, "g": 4676, "deri": 81.4}, {"m": 5, "d": 30, "kishu": "2", "samai": 520, "g": 5268, "deri": 103.3}, {"m": 5, "d": 30, "kishu": "5", "samai": 430, "g": 5173, "deri": 102.8}, {"m": 5, "d": 30, "kishu": "7", "samai": 88, "g": 4711, "deri": 100.6}, {"m": 5, "d": 29, "kishu": "スマスロ モンスターハンターライズ", "samai": 2582, "g": 4654, "deri": 118.5}, {"m": 5, "d": 29, "kishu": "スマスロ マギアレコード 魔法少女まどか☆マギカ外伝", "samai": 1262, "g": 7943, "deri": 105.3}, {"m": 5, "d": 29, "kishu": "Lパチスロからくりサーカス", "samai": 1240, "g": 1718, "deri": 124.1}, {"m": 5, "d": 29, "kishu": "Lパチスロ かぐや様は告らせたい", "samai": 1174, "g": 4216, "deri": 109.3}, {"m": 5, "d": 29, "kishu": "スマスロヨルムンガンド", "samai": 1140, "g": 2948, "deri": 112.9}, {"m": 5, "d": 29, "kishu": "Lパチスロ 機動戦士ガンダムユニコーン 覚醒DRIVE", "samai": 1127, "g": 1272, "deri": 129.5}, {"m": 5, "d": 29, "kishu": "スマスロ鉄拳6", "samai": 1030, "g": 1243, "deri": 127.6}, {"m": 5, "d": 29, "kishu": "プリズムナナ", "samai": 900, "g": 4151, "deri": 107.2}, {"m": 5, "d": 29, "kishu": "Lパチスロ革命機ヴァルヴレイヴ2", "samai": 879, "g": 5458, "deri": 105.4}, {"m": 5, "d": 29, "kishu": "LBスロットGALFY", "samai": 790, "g": 3454, "deri": 107.6}, {"m": 5, "d": 29, "kishu": "新ハナビ", "samai": 760, "g": 3648, "deri": 106.9}, {"m": 5, "d": 29, "kishu": "ジャグラーガールズSS", "samai": 730, "g": 4285, "deri": 105.7}, {"m": 5, "d": 29, "kishu": "スマスロ 東京リベンジャーズ", "samai": 673, "g": 1901, "deri": 111.8}, {"m": 5, "d": 29, "kishu": "Lタクトオーパス デスティニー", "samai": 665, "g": 7182, "deri": 103.1}, {"m": 5, "d": 29, "kishu": "Lスマスロ北斗の拳", "samai": 374, "g": 2466, "deri": 105.1}, {"m": 5, "d": 29, "kishu": "もっと！クレアの秘宝伝　女神の歌声と太陽の子供達", "samai": 373, "g": 1960, "deri": 106.3}, {"m": 5, "d": 29, "kishu": "スマスロ スーパーリオエース2", "samai": 278, "g": 5194, "deri": 101.8}, {"m": 5, "d": 29, "kishu": "L東京喰種", "samai": 263, "g": 3906, "deri": 102.2}, {"m": 5, "d": 29, "kishu": "A-SLOT+ ディスクアップ ULTRAREMIX", "samai": 256, "g": 3770, "deri": 102.3}, {"m": 5, "d": 29, "kishu": "ウルトラミラクルジャグラー", "samai": 180, "g": 4462, "deri": 101.3}, {"m": 5, "d": 29, "kishu": "ゴーゴージャグラー３", "samai": 119, "g": 5000, "deri": 100.8}, {"m": 5, "d": 29, "kishu": "スマスロモンキーターンV", "samai": 103, "g": 2175, "deri": 101.6}, {"m": 5, "d": 29, "kishu": "スマスロ北斗の拳 転生の章2", "samai": 24, "g": 2912, "deri": 100.3}, {"m": 5, "d": 29, "kishu": "スロット ゾンビランドサガ", "samai": -50, "g": 1872, "deri": 99.1}, {"m": 5, "d": 29, "kishu": "スマスロバジリスク～甲賀忍法帖～絆2 天膳 BLACK EDITION", "samai": -60, "g": 867, "deri": 97.7}, {"m": 5, "d": 29, "kishu": "ネオアイムジャグラーEX", "samai": -84, "g": 4489, "deri": 99.4}, {"m": 5, "d": 29, "kishu": "パチスロひぐらしのなく頃に祭２", "samai": -100, "g": 1431, "deri": 96.7}, {"m": 5, "d": 29, "kishu": "スマスロ化物語", "samai": -150, "g": 2908, "deri": 97.9}, {"m": 5, "d": 29, "kishu": "アレックス ブライト", "samai": -200, "g": 955, "deri": 92.9}, {"m": 5, "d": 29, "kishu": "マイジャグラーV", "samai": -200, "g": 4948, "deri": 98.6}, {"m": 5, "d": 29, "kishu": "スマスロ 攻殻機動隊", "samai": -200, "g": 2270, "deri": 96.4}, {"m": 5, "d": 29, "kishu": "Lパチスロうみねこのなく頃に2", "samai": -250, "g": 4185, "deri": 97.3}, {"m": 5, "d": 29, "kishu": "ハッピージャグラーＶＩＩＩ", "samai": -250, "g": 3543, "deri": 96.0}, {"m": 5, "d": 29, "kishu": "スマスロ ゴッドイーター リザレクション", "samai": -250, "g": 1985, "deri": 92.7}, {"m": 5, "d": 29, "kishu": "ファンキージャグラー２ＫＴ", "samai": -500, "g": 4154, "deri": 96.0}, {"m": 5, "d": 29, "kishu": "L無職転生～異世界行ったら本気だす～", "samai": -500, "g": 1716, "deri": 86.9}, {"m": 5, "d": 29, "kishu": "L ToLOVEるダークネス TRANCE ver.8.7", "samai": -500, "g": 2914, "deri": 91.8}, {"m": 5, "d": 29, "kishu": "スマスロ ミリオンゴッド-神々の軌跡-", "samai": -750, "g": 5325, "deri": 95.1}, {"m": 5, "d": 29, "kishu": "SHAKE BONUS TRIGGER", "samai": -750, "g": 3177, "deri": 90.9}, {"m": 5, "d": 29, "kishu": "Lパチスロ炎炎ノ消防隊2", "samai": -750, "g": 2489, "deri": 87.7}, {"m": 5, "d": 29, "kishu": "スマスロ 甲鉄城のカバネリ 海門決戦", "samai": -750, "g": 3776, "deri": 91.8}, {"m": 5, "d": 29, "kishu": "スマスロ サンダーV", "samai": -750, "g": 1296, "deri": 75.2}, {"m": 5, "d": 29, "kishu": "スマスロ バイオハザードRE:3", "samai": -1000, "g": 2287, "deri": 83.7}, {"m": 5, "d": 29, "kishu": "A-SLOT+異世界かるてっとBT", "samai": -1250, "g": 2749, "deri": 83.4}, {"m": 5, "d": 29, "kishu": "L虚構推理", "samai": -1500, "g": 3277, "deri": 84.3}, {"m": 5, "d": 29, "kishu": "0", "samai": 50, "g": 4104, "deri": 100.4}, {"m": 5, "d": 29, "kishu": "2", "samai": 389, "g": 3327, "deri": 103.9}, {"m": 5, "d": 29, "kishu": "3", "samai": 197, "g": 3609, "deri": 101.8}, {"m": 5, "d": 29, "kishu": "5", "samai": 7, "g": 3990, "deri": 100.1}, {"m": 5, "d": 29, "kishu": "6", "samai": 950, "g": 3507, "deri": 109.0}, {"m": 5, "d": 29, "kishu": "7", "samai": 81, "g": 4224, "deri": 100.6}, {"m": 5, "d": 28, "kishu": "Lパチスロ炎炎ノ消防隊2", "samai": 3428, "g": 8529, "deri": 113.4}, {"m": 5, "d": 28, "kishu": "スマスロ北斗の拳 転生の章2", "samai": 2494, "g": 5980, "deri": 113.9}, {"m": 5, "d": 28, "kishu": "Lパチスロ かぐや様は告らせたい", "samai": 1306, "g": 3788, "deri": 111.5}, {"m": 5, "d": 28, "kishu": "L東京喰種", "samai": 920, "g": 5202, "deri": 105.9}, {"m": 5, "d": 28, "kishu": "Lパチスロ革命機ヴァルヴレイヴ2", "samai": 877, "g": 5353, "deri": 105.5}, {"m": 5, "d": 28, "kishu": "ファンキージャグラー２ＫＴ", "samai": 860, "g": 4835, "deri": 105.9}, {"m": 5, "d": 28, "kishu": "ネオアイムジャグラーEX", "samai": 743, "g": 5490, "deri": 104.5}, {"m": 5, "d": 28, "kishu": "スマスロ 東京リベンジャーズ", "samai": 695, "g": 1112, "deri": 120.8}, {"m": 5, "d": 28, "kishu": "アレックス ブライト", "samai": 570, "g": 1432, "deri": 113.3}, {"m": 5, "d": 28, "kishu": "スマスロ鉄拳6", "samai": 507, "g": 943, "deri": 117.9}, {"m": 5, "d": 28, "kishu": "スマスロヨルムンガンド", "samai": 438, "g": 1189, "deri": 112.3}, {"m": 5, "d": 28, "kishu": "LBスロットGALFY", "samai": 415, "g": 2067, "deri": 106.7}, {"m": 5, "d": 28, "kishu": "新ハナビ", "samai": 337, "g": 2431, "deri": 104.6}, {"m": 5, "d": 28, "kishu": "パチスロひぐらしのなく頃に祭２", "samai": 320, "g": 1655, "deri": 106.4}, {"m": 5, "d": 28, "kishu": "A-SLOT+ ディスクアップ ULTRAREMIX", "samai": 296, "g": 3589, "deri": 102.7}, {"m": 5, "d": 28, "kishu": "スロット ゾンビランドサガ", "samai": 267, "g": 680, "deri": 113.1}, {"m": 5, "d": 28, "kishu": "スマスロ 攻殻機動隊", "samai": 262, "g": 3848, "deri": 102.3}, {"m": 5, "d": 28, "kishu": "L虚構推理", "samai": 243, "g": 3171, "deri": 102.6}, {"m": 5, "d": 28, "kishu": "スマスロ モンスターハンターライズ", "samai": 238, "g": 1298, "deri": 106.1}, {"m": 5, "d": 28, "kishu": "スマスロモンキーターンV", "samai": 188, "g": 3307, "deri": 101.9}, {"m": 5, "d": 28, "kishu": "スマスロ バイオハザードRE:3", "samai": 172, "g": 1932, "deri": 103.0}, {"m": 5, "d": 28, "kishu": "スマスロ ミリオンゴッド-神々の軌跡-", "samai": 171, "g": 6719, "deri": 100.8}, {"m": 5, "d": 28, "kishu": "A-SLOT+異世界かるてっとBT", "samai": 140, "g": 2530, "deri": 101.8}, {"m": 5, "d": 28, "kishu": "ジャグラーガールズSS", "samai": 130, "g": 3859, "deri": 101.1}, {"m": 5, "d": 28, "kishu": "もっと！クレアの秘宝伝　女神の歌声と太陽の子供達", "samai": 113, "g": 305, "deri": 112.4}, {"m": 5, "d": 28, "kishu": "ウルトラミラクルジャグラー", "samai": 104, "g": 3791, "deri": 100.9}, {"m": 5, "d": 28, "kishu": "スマスロバジリスク～甲賀忍法帖～絆2 天膳 BLACK EDITION", "samai": 97, "g": 1818, "deri": 101.8}, {"m": 5, "d": 28, "kishu": "スマスロ ゴッドイーター リザレクション", "samai": -26, "g": 861, "deri": 99.0}, {"m": 5, "d": 28, "kishu": "Lパチスロうみねこのなく頃に2", "samai": -33, "g": 3264, "deri": 99.7}, {"m": 5, "d": 28, "kishu": "マイジャグラーV", "samai": -44, "g": 5948, "deri": 99.8}, {"m": 5, "d": 28, "kishu": "ハッピージャグラーＶＩＩＩ", "samai": -90, "g": 4285, "deri": 99.3}, {"m": 5, "d": 28, "kishu": "Lパチスロからくりサーカス", "samai": -100, "g": 1571, "deri": 97.7}, {"m": 5, "d": 28, "kishu": "プリズムナナ", "samai": -100, "g": 2970, "deri": 98.5}, {"m": 5, "d": 28, "kishu": "SHAKE BONUS TRIGGER", "samai": -150, "g": 1820, "deri": 97.3}, {"m": 5, "d": 28, "kishu": "スマスロ スーパーリオエース2", "samai": -150, "g": 3615, "deri": 98.4}, {"m": 5, "d": 28, "kishu": "ゴーゴージャグラー３", "samai": -250, "g": 4568, "deri": 98.2}, {"m": 5, "d": 28, "kishu": "スマスロ マギアレコード 魔法少女まどか☆マギカ外伝", "samai": -250, "g": 1080, "deri": 90.3}, {"m": 5, "d": 28, "kishu": "Lスマスロ北斗の拳", "samai": -250, "g": 1356, "deri": 89.9}, {"m": 5, "d": 28, "kishu": "スマスロ サンダーV", "samai": -250, "g": 1309, "deri": 89.0}, {"m": 5, "d": 28, "kishu": "Lパチスロ 機動戦士ガンダムユニコーン 覚醒DRIVE", "samai": -250, "g": 932, "deri": 83.5}, {"m": 5, "d": 28, "kishu": "スマスロ化物語", "samai": -750, "g": 1397, "deri": 77.5}, {"m": 5, "d": 28, "kishu": "スマスロ 甲鉄城のカバネリ 海門決戦", "samai": -1000, "g": 4899, "deri": 92.1}, {"m": 5, "d": 28, "kishu": "L ToLOVEるダークネス TRANCE ver.8.7", "samai": -1250, "g": 2843, "deri": 82.8}, {"m": 5, "d": 28, "kishu": "L無職転生～異世界行ったら本気だす～", "samai": -1750, "g": 3093, "deri": 80.7}, {"m": 5, "d": 28, "kishu": "Lタクトオーパス デスティニー", "samai": -2750, "g": 4900, "deri": 81.1}, {"m": 5, "d": 28, "kishu": "1", "samai": 366, "g": 3436, "deri": 103.6}, {"m": 5, "d": 28, "kishu": "2", "samai": 157, "g": 4181, "deri": 101.2}, {"m": 5, "d": 28, "kishu": "3", "samai": 446, "g": 3416, "deri": 104.3}, {"m": 5, "d": 28, "kishu": "4", "samai": 785, "g": 3817, "deri": 106.9}, {"m": 5, "d": 28, "kishu": "5", "samai": 447, "g": 3838, "deri": 103.9}, {"m": 5, "d": 28, "kishu": "6", "samai": 567, "g": 3603, "deri": 105.2}, {"m": 5, "d": 28, "kishu": "8", "samai": 355, "g": 4218, "deri": 102.8}, {"m": 5, "d": 28, "kishu": "9", "samai": 81, "g": 3611, "deri": 100.8}, {"m": 5, "d": 27, "kishu": "L無職転生～異世界行ったら本気だす～", "samai": 2435, "g": 2488, "deri": 132.6}, {"m": 5, "d": 27, "kishu": "スマスロ ゴッドイーター リザレクション", "samai": 1364, "g": 3623, "deri": 112.6}, {"m": 5, "d": 27, "kishu": "Lタクトオーパス デスティニー", "samai": 1340, "g": 6853, "deri": 106.5}, {"m": 5, "d": 27, "kishu": "Lパチスロ革命機ヴァルヴレイヴ2", "samai": 1258, "g": 6302, "deri": 106.7}, {"m": 5, "d": 27, "kishu": "Lパチスロうみねこのなく頃に2", "samai": 1183, "g": 6000, "deri": 106.6}, {"m": 5, "d": 27, "kishu": "スマスロ モンスターハンターライズ", "samai": 1138, "g": 2260, "deri": 116.8}, {"m": 5, "d": 27, "kishu": "A-SLOT+異世界かるてっとBT", "samai": 923, "g": 4499, "deri": 106.8}, {"m": 5, "d": 27, "kishu": "スマスロ マギアレコード 魔法少女まどか☆マギカ外伝", "samai": 823, "g": 3763, "deri": 107.3}, {"m": 5, "d": 27, "kishu": "スマスロ北斗の拳 転生の章2", "samai": 751, "g": 6469, "deri": 103.9}, {"m": 5, "d": 27, "kishu": "プリズムナナ", "samai": 485, "g": 2297, "deri": 107.0}, {"m": 5, "d": 27, "kishu": "スマスロモンキーターンV", "samai": 335, "g": 4964, "deri": 102.3}, {"m": 5, "d": 27, "kishu": "パチスロひぐらしのなく頃に祭２", "samai": 270, "g": 1567, "deri": 105.7}, {"m": 5, "d": 27, "kishu": "ネオアイムジャグラーEX", "samai": 228, "g": 5735, "deri": 101.3}, {"m": 5, "d": 27, "kishu": "スマスロバジリスク～甲賀忍法帖～絆2 天膳 BLACK EDITION", "samai": 133, "g": 1572, "deri": 102.8}, {"m": 5, "d": 27, "kishu": "スマスロ バイオハザードRE:3", "samai": 101, "g": 3641, "deri": 100.9}, {"m": 5, "d": 27, "kishu": "L東京喰種", "samai": -7, "g": 6736, "deri": 100.0}, {"m": 5, "d": 27, "kishu": "スマスロ 東京リベンジャーズ", "samai": -63, "g": 2520, "deri": 99.2}, {"m": 5, "d": 27, "kishu": "新ハナビ", "samai": -67, "g": 1868, "deri": 98.8}, {"m": 5, "d": 27, "kishu": "ファンキージャグラー２ＫＴ", "samai": -78, "g": 4545, "deri": 99.4}, {"m": 5, "d": 27, "kishu": "アレックス ブライト", "samai": -100, "g": 2065, "deri": 97.6}, {"m": 5, "d": 27, "kishu": "スマスロ スーパーリオエース2", "samai": -150, "g": 4753, "deri": 98.9}, {"m": 5, "d": 27, "kishu": "マイジャグラーV", "samai": -150, "g": 6052, "deri": 99.0}, {"m": 5, "d": 27, "kishu": "スマスロ 攻殻機動隊", "samai": -150, "g": 3732, "deri": 98.4}, {"m": 5, "d": 27, "kishu": "ゴーゴージャグラー３", "samai": -200, "g": 4353, "deri": 98.4}, {"m": 5, "d": 27, "kishu": "Lスマスロ北斗の拳", "samai": -200, "g": 3088, "deri": 97.4}, {"m": 5, "d": 27, "kishu": "A-SLOT+ ディスクアップ ULTRAREMIX", "samai": -200, "g": 2618, "deri": 96.9}, {"m": 5, "d": 27, "kishu": "ジャグラーガールズSS", "samai": -250, "g": 3421, "deri": 97.3}, {"m": 5, "d": 27, "kishu": "スマスロヨルムンガンド", "samai": -250, "g": 3557, "deri": 97.2}, {"m": 5, "d": 27, "kishu": "スマスロ サンダーV", "samai": -250, "g": 1638, "deri": 91.9}, {"m": 5, "d": 27, "kishu": "もっと！クレアの秘宝伝　女神の歌声と太陽の子供達", "samai": -250, "g": 1058, "deri": 86.3}, {"m": 5, "d": 27, "kishu": "ウルトラミラクルジャグラー", "samai": -250, "g": 5024, "deri": 97.1}, {"m": 5, "d": 27, "kishu": "Lパチスロからくりサーカス", "samai": -250, "g": 452, "deri": 67.7}, {"m": 5, "d": 27, "kishu": "スマスロ化物語", "samai": -500, "g": 2138, "deri": 92.0}, {"m": 5, "d": 27, "kishu": "スロット ゾンビランドサガ", "samai": -500, "g": 1651, "deri": 89.4}, {"m": 5, "d": 27, "kishu": "ハッピージャグラーＶＩＩＩ", "samai": -500, "g": 4142, "deri": 95.5}, {"m": 5, "d": 27, "kishu": "スマスロ ミリオンゴッド-神々の軌跡-", "samai": -500, "g": 7793, "deri": 97.5}, {"m": 5, "d": 27, "kishu": "スマスロ鉄拳6", "samai": -500, "g": 1126, "deri": 78.7}, {"m": 5, "d": 27, "kishu": "SHAKE BONUS TRIGGER", "samai": -750, "g": 1871, "deri": 85.5}, {"m": 5, "d": 27, "kishu": "Lパチスロ かぐや様は告らせたい", "samai": -750, "g": 2919, "deri": 89.2}, {"m": 5, "d": 27, "kishu": "LBスロットGALFY", "samai": -1000, "g": 4423, "deri": 92.2}, {"m": 5, "d": 27, "kishu": "L虚構推理", "samai": -1000, "g": 5217, "deri": 93.1}, {"m": 5, "d": 27, "kishu": "Lパチスロ 機動戦士ガンダムユニコーン 覚醒DRIVE", "samai": -1000, "g": 2358, "deri": 83.1}, {"m": 5, "d": 27, "kishu": "Lパチスロ炎炎ノ消防隊2", "samai": -1250, "g": 4655, "deri": 90.8}, {"m": 5, "d": 27, "kishu": "スマスロ 甲鉄城のカバネリ 海門決戦", "samai": -1250, "g": 5291, "deri": 90.7}, {"m": 5, "d": 27, "kishu": "L ToLOVEるダークネス TRANCE ver.8.7", "samai": -2250, "g": 5870, "deri": 87.0}, {"m": 5, "d": 27, "kishu": "2", "samai": 233, "g": 3966, "deri": 102.0}, {"m": 5, "d": 27, "kishu": "4", "samai": 186, "g": 4232, "deri": 101.5}, {"m": 5, "d": 27, "kishu": "5", "samai": 214, "g": 4815, "deri": 101.5}, {"m": 5, "d": 27, "kishu": "6", "samai": 1332, "g": 4708, "deri": 109.4}, {"m": 5, "d": 27, "kishu": "9", "samai": 119, "g": 4344, "deri": 100.9}, {"m": 5, "d": 26, "kishu": "スマスロ 東京リベンジャーズ", "samai": 2523, "g": 8239, "deri": 110.2}, {"m": 5, "d": 26, "kishu": "スマスロ 甲鉄城のカバネリ 海門決戦", "samai": 2228, "g": 6209, "deri": 112.0}, {"m": 5, "d": 26, "kishu": "A-SLOT+異世界かるてっとBT", "samai": 2197, "g": 7186, "deri": 110.2}, {"m": 5, "d": 26, "kishu": "L東京喰種", "samai": 2113, "g": 7589, "deri": 109.3}, {"m": 5, "d": 26, "kishu": "スマスロ北斗の拳 転生の章2", "samai": 1741, "g": 4664, "deri": 112.4}, {"m": 5, "d": 26, "kishu": "スマスロ鉄拳6", "samai": 1737, "g": 4558, "deri": 112.7}, {"m": 5, "d": 26, "kishu": "スマスロ モンスターハンターライズ", "samai": 1314, "g": 3183, "deri": 113.8}, {"m": 5, "d": 26, "kishu": "LBスロットGALFY", "samai": 1250, "g": 4775, "deri": 108.7}, {"m": 5, "d": 26, "kishu": "スマスロ化物語", "samai": 1182, "g": 4448, "deri": 108.9}, {"m": 5, "d": 26, "kishu": "Lスマスロ北斗の拳", "samai": 1096, "g": 3856, "deri": 109.5}, {"m": 5, "d": 26, "kishu": "アレックス ブライト", "samai": 1043, "g": 3823, "deri": 109.1}, {"m": 5, "d": 26, "kishu": "スマスロ ミリオンゴッド-神々の軌跡-", "samai": 981, "g": 8180, "deri": 104.0}, {"m": 5, "d": 26, "kishu": "スマスロヨルムンガンド", "samai": 968, "g": 3061, "deri": 110.5}, {"m": 5, "d": 26, "kishu": "新ハナビ", "samai": 817, "g": 2651, "deri": 110.3}, {"m": 5, "d": 26, "kishu": "スマスロ スーパーリオエース2", "samai": 584, "g": 5933, "deri": 103.3}, {"m": 5, "d": 26, "kishu": "スマスロ マギアレコード 魔法少女まどか☆マギカ外伝", "samai": 534, "g": 5264, "deri": 103.4}, {"m": 5, "d": 26, "kishu": "スマスロ ゴッドイーター リザレクション", "samai": 494, "g": 3764, "deri": 104.4}, {"m": 5, "d": 26, "kishu": "Lパチスロからくりサーカス", "samai": 441, "g": 3305, "deri": 104.4}, {"m": 5, "d": 26, "kishu": "スマスロ サンダーV", "samai": 433, "g": 2459, "deri": 105.9}, {"m": 5, "d": 26, "kishu": "ファンキージャグラー２ＫＴ", "samai": 346, "g": 6015, "deri": 101.9}, {"m": 5, "d": 26, "kishu": "スロット ゾンビランドサガ", "samai": 277, "g": 2194, "deri": 104.2}, {"m": 5, "d": 26, "kishu": "ウルトラミラクルジャグラー", "samai": 178, "g": 4428, "deri": 101.3}, {"m": 5, "d": 26, "kishu": "ネオアイムジャグラーEX", "samai": 73, "g": 5822, "deri": 100.4}, {"m": 5, "d": 26, "kishu": "マイジャグラーV", "samai": -2, "g": 6237, "deri": 100.0}, {"m": 5, "d": 26, "kishu": "スマスロモンキーターンV", "samai": -70, "g": 4522, "deri": 99.5}, {"m": 5, "d": 26, "kishu": "Lパチスロ炎炎ノ消防隊2", "samai": -100, "g": 6982, "deri": 99.5}, {"m": 5, "d": 26, "kishu": "ゴーゴージャグラー３", "samai": -100, "g": 4471, "deri": 99.1}, {"m": 5, "d": 26, "kishu": "Lパチスロうみねこのなく頃に2", "samai": -200, "g": 4328, "deri": 98.4}, {"m": 5, "d": 26, "kishu": "もっと！クレアの秘宝伝　女神の歌声と太陽の子供達", "samai": -200, "g": 308, "deri": 74.7}, {"m": 5, "d": 26, "kishu": "A-SLOT+ ディスクアップ ULTRAREMIX", "samai": -200, "g": 3290, "deri": 97.6}, {"m": 5, "d": 26, "kishu": "ジャグラーガールズSS", "samai": -250, "g": 4779, "deri": 97.6}, {"m": 5, "d": 26, "kishu": "SHAKE BONUS TRIGGER", "samai": -250, "g": 4743, "deri": 97.3}, {"m": 5, "d": 26, "kishu": "L虚構推理", "samai": -250, "g": 3884, "deri": 96.4}, {"m": 5, "d": 26, "kishu": "Lパチスロ革命機ヴァルヴレイヴ2", "samai": -250, "g": 8010, "deri": 98.2}, {"m": 5, "d": 26, "kishu": "ハッピージャグラーＶＩＩＩ", "samai": -250, "g": 5606, "deri": 97.1}, {"m": 5, "d": 26, "kishu": "スマスロ バイオハザードRE:3", "samai": -500, "g": 4582, "deri": 96.0}, {"m": 5, "d": 26, "kishu": "Lパチスロ かぐや様は告らせたい", "samai": -500, "g": 3549, "deri": 94.6}, {"m": 5, "d": 26, "kishu": "L ToLOVEるダークネス TRANCE ver.8.7", "samai": -500, "g": 4443, "deri": 95.2}, {"m": 5, "d": 26, "kishu": "パチスロひぐらしのなく頃に祭２", "samai": -750, "g": 2392, "deri": 86.5}, {"m": 5, "d": 26, "kishu": "Lタクトオーパス デスティニー", "samai": -1000, "g": 5579, "deri": 93.9}, {"m": 5, "d": 26, "kishu": "スマスロバジリスク～甲賀忍法帖～絆2 天膳 BLACK EDITION", "samai": -1000, "g": 3222, "deri": 88.2}, {"m": 5, "d": 26, "kishu": "Lパチスロ 機動戦士ガンダムユニコーン 覚醒DRIVE", "samai": -1000, "g": 1682, "deri": 77.4}, {"m": 5, "d": 26, "kishu": "スマスロ 攻殻機動隊", "samai": -1250, "g": 4634, "deri": 89.2}, {"m": 5, "d": 26, "kishu": "プリズムナナ", "samai": -2000, "g": 2407, "deri": 70.2}, {"m": 5, "d": 26, "kishu": "L無職転生～異世界行ったら本気だす～", "samai": -2250, "g": 4357, "deri": 81.9}, {"m": 5, "d": 26, "kishu": "0", "samai": 856, "g": 5449, "deri": 105.2}, {"m": 5, "d": 26, "kishu": "1", "samai": 964, "g": 5499, "deri": 105.8}, {"m": 5, "d": 26, "kishu": "2", "samai": 598, "g": 5718, "deri": 103.5}, {"m": 5, "d": 26, "kishu": "3", "samai": 346, "g": 4790, "deri": 102.4}, {"m": 5, "d": 26, "kishu": "4", "samai": 10, "g": 5411, "deri": 100.1}, {"m": 5, "d": 26, "kishu": "6", "samai": 128, "g": 4594, "deri": 100.9}, {"m": 5, "d": 26, "kishu": "7", "samai": 786, "g": 5531, "deri": 104.7}, {"m": 5, "d": 26, "kishu": "8", "samai": 315, "g": 5276, "deri": 102.0}, {"m": 5, "d": 26, "kishu": "9", "samai": 103, "g": 5132, "deri": 100.7}, {"m": 5, "d": 25, "kishu": "Lタクトオーパス デスティニー", "samai": 6995, "g": 6183, "deri": 137.7}, {"m": 5, "d": 25, "kishu": "プリズムナナ", "samai": 5595, "g": 4996, "deri": 137.3}, {"m": 5, "d": 25, "kishu": "スマスロ ゴッドイーター リザレクション", "samai": 1934, "g": 1307, "deri": 149.3}, {"m": 5, "d": 25, "kishu": "スマスロ 東京リベンジャーズ", "samai": 1687, "g": 2945, "deri": 119.1}, {"m": 5, "d": 25, "kishu": "Lパチスロ革命機ヴァルヴレイヴ2", "samai": 1290, "g": 7903, "deri": 105.4}, {"m": 5, "d": 25, "kishu": "Lスマスロ北斗の拳", "samai": 1120, "g": 1089, "deri": 134.3}, {"m": 5, "d": 25, "kishu": "スマスロ ミリオンゴッド-神々の軌跡-", "samai": 960, "g": 6076, "deri": 105.3}, {"m": 5, "d": 25, "kishu": "スマスロ鉄拳6", "samai": 630, "g": 753, "deri": 127.9}, {"m": 5, "d": 25, "kishu": "スロット ゾンビランドサガ", "samai": 503, "g": 2416, "deri": 106.9}, {"m": 5, "d": 25, "kishu": "ネオアイムジャグラーEX", "samai": 482, "g": 4941, "deri": 103.2}, {"m": 5, "d": 25, "kishu": "スマスロモンキーターンV", "samai": 458, "g": 4829, "deri": 103.2}, {"m": 5, "d": 25, "kishu": "Lパチスロうみねこのなく頃に2", "samai": 457, "g": 3567, "deri": 104.3}, {"m": 5, "d": 25, "kishu": "新ハナビ", "samai": 443, "g": 3389, "deri": 104.4}, {"m": 5, "d": 25, "kishu": "A-SLOT+異世界かるてっとBT", "samai": 313, "g": 4950, "deri": 102.1}, {"m": 5, "d": 25, "kishu": "L虚構推理", "samai": 293, "g": 2305, "deri": 104.2}, {"m": 5, "d": 25, "kishu": "ファンキージャグラー２ＫＴ", "samai": 284, "g": 5387, "deri": 101.8}, {"m": 5, "d": 25, "kishu": "LBスロットGALFY", "samai": 250, "g": 3275, "deri": 102.5}, {"m": 5, "d": 25, "kishu": "ウルトラミラクルジャグラー", "samai": 239, "g": 4571, "deri": 101.7}, {"m": 5, "d": 25, "kishu": "マイジャグラーV", "samai": 229, "g": 5593, "deri": 101.4}, {"m": 5, "d": 25, "kishu": "ジャグラーガールズSS", "samai": 210, "g": 4368, "deri": 101.6}, {"m": 5, "d": 25, "kishu": "スマスロ マギアレコード 魔法少女まどか☆マギカ外伝", "samai": 174, "g": 1986, "deri": 102.9}, {"m": 5, "d": 25, "kishu": "L東京喰種", "samai": 173, "g": 5328, "deri": 101.1}, {"m": 5, "d": 25, "kishu": "A-SLOT+ ディスクアップ ULTRAREMIX", "samai": 74, "g": 1920, "deri": 101.3}, {"m": 5, "d": 25, "kishu": "アレックス ブライト", "samai": 23, "g": 1978, "deri": 100.4}, {"m": 5, "d": 25, "kishu": "スマスロ 攻殻機動隊", "samai": -12, "g": 2963, "deri": 99.9}, {"m": 5, "d": 25, "kishu": "ゴーゴージャグラー３", "samai": -37, "g": 5729, "deri": 99.8}, {"m": 5, "d": 25, "kishu": "Lパチスロからくりサーカス", "samai": -77, "g": 475, "deri": 94.6}, {"m": 5, "d": 25, "kishu": "ハッピージャグラーＶＩＩＩ", "samai": -100, "g": 5247, "deri": 99.3}, {"m": 5, "d": 25, "kishu": "もっと！クレアの秘宝伝　女神の歌声と太陽の子供達", "samai": -100, "g": 176, "deri": 72.9}, {"m": 5, "d": 25, "kishu": "スマスロ スーパーリオエース2", "samai": -100, "g": 4118, "deri": 98.8}, {"m": 5, "d": 25, "kishu": "スマスロバジリスク～甲賀忍法帖～絆2 天膳 BLACK EDITION", "samai": -150, "g": 3710, "deri": 98.3}, {"m": 5, "d": 25, "kishu": "Lパチスロ炎炎ノ消防隊2", "samai": -250, "g": 2423, "deri": 96.3}, {"m": 5, "d": 25, "kishu": "Lパチスロ かぐや様は告らせたい", "samai": -250, "g": 2098, "deri": 93.5}, {"m": 5, "d": 25, "kishu": "スマスロ バイオハザードRE:3", "samai": -250, "g": 1614, "deri": 91.0}, {"m": 5, "d": 25, "kishu": "SHAKE BONUS TRIGGER", "samai": -500, "g": 3244, "deri": 94.8}, {"m": 5, "d": 25, "kishu": "スマスロヨルムンガンド", "samai": -500, "g": 530, "deri": 66.7}, {"m": 5, "d": 25, "kishu": "スマスロ北斗の拳 転生の章2", "samai": -500, "g": 2810, "deri": 92.1}, {"m": 5, "d": 25, "kishu": "スマスロ サンダーV", "samai": -750, "g": 2663, "deri": 88.3}, {"m": 5, "d": 25, "kishu": "スマスロ モンスターハンターライズ", "samai": -1000, "g": 2309, "deri": 85.1}, {"m": 5, "d": 25, "kishu": "L無職転生～異世界行ったら本気だす～", "samai": -1000, "g": 3388, "deri": 89.7}, {"m": 5, "d": 25, "kishu": "Lパチスロ 機動戦士ガンダムユニコーン 覚醒DRIVE", "samai": -1000, "g": 982, "deri": 63.8}, {"m": 5, "d": 25, "kishu": "スマスロ化物語", "samai": -1000, "g": 3691, "deri": 89.7}, {"m": 5, "d": 25, "kishu": "スマスロ 甲鉄城のカバネリ 海門決戦", "samai": -1500, "g": 3963, "deri": 87.2}, {"m": 5, "d": 25, "kishu": "L ToLOVEるダークネス TRANCE ver.8.7", "samai": -2000, "g": 4455, "deri": 83.5}, {"m": 5, "d": 25, "kishu": "1", "samai": 396, "g": 3850, "deri": 103.4}, {"m": 5, "d": 25, "kishu": "2", "samai": 521, "g": 3431, "deri": 105.1}, {"m": 5, "d": 25, "kishu": "3", "samai": 107, "g": 3777, "deri": 100.9}, {"m": 5, "d": 25, "kishu": "5", "samai": 425, "g": 4408, "deri": 103.2}, {"m": 5, "d": 25, "kishu": "7", "samai": 609, "g": 4799, "deri": 104.2}, {"m": 5, "d": 25, "kishu": "8", "samai": 675, "g": 4261, "deri": 105.3}, {"m": 5, "d": 24, "kishu": "L ToLOVEるダークネス TRANCE ver.8.7", "samai": 2135, "g": 3891, "deri": 118.3}, {"m": 5, "d": 24, "kishu": "パチスロひぐらしのなく頃に祭２", "samai": 1925, "g": 5300, "deri": 112.1}, {"m": 5, "d": 24, "kishu": "A-SLOT+ ディスクアップ ULTRAREMIX", "samai": 1180, "g": 4612, "deri": 108.5}, {"m": 5, "d": 24, "kishu": "Lパチスロ 機動戦士ガンダムユニコーン 覚醒DRIVE", "samai": 897, "g": 1222, "deri": 124.5}, {"m": 5, "d": 24, "kishu": "SHAKE BONUS TRIGGER", "samai": 813, "g": 6417, "deri": 104.2}, {"m": 5, "d": 24, "kishu": "もっと！クレアの秘宝伝　女神の歌声と太陽の子供達", "samai": 597, "g": 2324, "deri": 108.6}, {"m": 5, "d": 24, "kishu": "Lパチスロ革命機ヴァルヴレイヴ2", "samai": 580, "g": 4609, "deri": 104.2}, {"m": 5, "d": 24, "kishu": "L東京喰種", "samai": 529, "g": 5489, "deri": 103.2}, {"m": 5, "d": 24, "kishu": "LBパチスロ ヱヴァンゲリヲン～約束の扉～", "samai": 510, "g": 5868, "deri": 102.9}, {"m": 5, "d": 24, "kishu": "スマスロバジリスク～甲賀忍法帖～絆2 天膳 BLACK EDITION", "samai": 497, "g": 3484, "deri": 104.8}, {"m": 5, "d": 24, "kishu": "Lパチスロうみねこのなく頃に2", "samai": 492, "g": 5502, "deri": 103.0}, {"m": 5, "d": 24, "kishu": "スマスロモンキーターンV", "samai": 456, "g": 3311, "deri": 104.6}, {"m": 5, "d": 24, "kishu": "ウルトラミラクルジャグラー", "samai": 429, "g": 3292, "deri": 104.3}, {"m": 5, "d": 24, "kishu": "ジャグラーガールズSS", "samai": 422, "g": 3647, "deri": 103.9}, {"m": 5, "d": 24, "kishu": "ネオアイムジャグラーEX", "samai": 381, "g": 4419, "deri": 102.9}, {"m": 5, "d": 24, "kishu": "Lパチスロ かぐや様は告らせたい", "samai": 327, "g": 4816, "deri": 102.3}, {"m": 5, "d": 24, "kishu": "スマスロ サンダーV", "samai": 320, "g": 4270, "deri": 102.5}, {"m": 5, "d": 24, "kishu": "スマスロ 甲鉄城のカバネリ 海門決戦", "samai": 308, "g": 5246, "deri": 102.0}, {"m": 5, "d": 24, "kishu": "マイジャグラーV", "samai": 84, "g": 5151, "deri": 100.5}, {"m": 5, "d": 24, "kishu": "ゴーゴージャグラー３", "samai": 76, "g": 4593, "deri": 100.5}, {"m": 5, "d": 24, "kishu": "スマスロ マギアレコード 魔法少女まどか☆マギカ外伝", "samai": 32, "g": 1865, "deri": 100.6}, {"m": 5, "d": 24, "kishu": "スマスロ 東京リベンジャーズ", "samai": -100, "g": 1989, "deri": 98.1}, {"m": 5, "d": 24, "kishu": "Lパチスロからくりサーカス", "samai": -100, "g": 605, "deri": 92.0}, {"m": 5, "d": 24, "kishu": "スマスロ ミリオンゴッド-神々の軌跡-", "samai": -150, "g": 5616, "deri": 99.0}, {"m": 5, "d": 24, "kishu": "スマスロ鉄拳6", "samai": -150, "g": 1604, "deri": 96.2}, {"m": 5, "d": 24, "kishu": "スマスロ バイオハザードRE:3", "samai": -150, "g": 3280, "deri": 98.0}, {"m": 5, "d": 24, "kishu": "ファンキージャグラー２ＫＴ", "samai": -200, "g": 3700, "deri": 98.1}, {"m": 5, "d": 24, "kishu": "Lパチスロ炎炎ノ消防隊2", "samai": -250, "g": 5556, "deri": 97.9}, {"m": 5, "d": 24, "kishu": "ハッピージャグラーＶＩＩＩ", "samai": -500, "g": 2432, "deri": 91.6}, {"m": 5, "d": 24, "kishu": "スマスロ ゴッドイーター リザレクション", "samai": -500, "g": 1281, "deri": 81.6}, {"m": 5, "d": 24, "kishu": "新ハナビ", "samai": -750, "g": 4880, "deri": 94.8}, {"m": 5, "d": 24, "kishu": "アレックス ブライト", "samai": -750, "g": 2163, "deri": 86.4}, {"m": 5, "d": 24, "kishu": "スマスロヨルムンガンド", "samai": -750, "g": 1437, "deri": 77.6}, {"m": 5, "d": 24, "kishu": "スマスロ モンスターハンターライズ", "samai": -1000, "g": 4569, "deri": 92.6}, {"m": 5, "d": 24, "kishu": "Lスマスロ北斗の拳", "samai": -1000, "g": 1881, "deri": 82.1}, {"m": 5, "d": 24, "kishu": "スマスロ北斗の拳 転生の章2", "samai": -1000, "g": 3146, "deri": 88.0}, {"m": 5, "d": 24, "kishu": "スロット ゾンビランドサガ", "samai": -1000, "g": 2250, "deri": 82.4}, {"m": 5, "d": 24, "kishu": "L無職転生～異世界行ったら本気だす～", "samai": -1000, "g": 2833, "deri": 85.9}, {"m": 5, "d": 24, "kishu": "スマスロ化物語", "samai": -1250, "g": 4005, "deri": 88.6}, {"m": 5, "d": 24, "kishu": "スマスロ 攻殻機動隊", "samai": -1250, "g": 4238, "deri": 89.0}, {"m": 5, "d": 24, "kishu": "プリズムナナ", "samai": -1750, "g": 2426, "deri": 76.0}, {"m": 5, "d": 24, "kishu": "スマスロ スーパーリオエース2", "samai": -2250, "g": 5491, "deri": 86.3}, {"m": 5, "d": 24, "kishu": "L虚構推理", "samai": -2250, "g": 4075, "deri": 81.2}, {"m": 5, "d": 24, "kishu": "Lタクトオーパス デスティニー", "samai": -3000, "g": 5288, "deri": 81.0}, {"m": 5, "d": 24, "kishu": "1", "samai": 451, "g": 4148, "deri": 103.6}, {"m": 5, "d": 24, "kishu": "2", "samai": 148, "g": 3395, "deri": 101.5}, {"m": 5, "d": 24, "kishu": "7", "samai": 727, "g": 4304, "deri": 105.6}, {"m": 5, "d": 23, "kishu": "L無職転生～異世界行ったら本気だす～", "samai": 3980, "g": 3619, "deri": 136.7}, {"m": 5, "d": 23, "kishu": "L東京喰種", "samai": 2646, "g": 6869, "deri": 112.8}, {"m": 5, "d": 23, "kishu": "L ToLOVEるダークネス TRANCE ver.8.7", "samai": 1225, "g": 4027, "deri": 110.1}, {"m": 5, "d": 23, "kishu": "Lスマスロ北斗の拳", "samai": 1104, "g": 3616, "deri": 110.2}, {"m": 5, "d": 23, "kishu": "スマスロ 甲鉄城のカバネリ 海門決戦", "samai": 1089, "g": 5553, "deri": 106.5}, {"m": 5, "d": 23, "kishu": "スマスロバジリスク～甲賀忍法帖～絆2 天膳 BLACK EDITION", "samai": 970, "g": 2091, "deri": 115.5}, {"m": 5, "d": 23, "kishu": "ハッピージャグラーＶＩＩＩ", "samai": 868, "g": 4622, "deri": 106.3}, {"m": 5, "d": 23, "kishu": "スマスロ化物語", "samai": 732, "g": 5304, "deri": 104.6}, {"m": 5, "d": 23, "kishu": "スマスロ北斗の拳 転生の章2", "samai": 662, "g": 3202, "deri": 106.9}, {"m": 5, "d": 23, "kishu": "スマスロ鉄拳6", "samai": 583, "g": 2609, "deri": 107.5}, {"m": 5, "d": 23, "kishu": "スマスロ マギアレコード 魔法少女まどか☆マギカ外伝", "samai": 554, "g": 2524, "deri": 107.3}, {"m": 5, "d": 23, "kishu": "スマスロ ゴッドイーター リザレクション", "samai": 522, "g": 3991, "deri": 104.4}, {"m": 5, "d": 23, "kishu": "ウルトラミラクルジャグラー", "samai": 520, "g": 4429, "deri": 103.9}, {"m": 5, "d": 23, "kishu": "スマスロ サンダーV", "samai": 500, "g": 4684, "deri": 103.6}, {"m": 5, "d": 23, "kishu": "スマスロ 攻殻機動隊", "samai": 464, "g": 5147, "deri": 103.0}, {"m": 5, "d": 23, "kishu": "もっと！クレアの秘宝伝　女神の歌声と太陽の子供達", "samai": 337, "g": 1383, "deri": 108.1}, {"m": 5, "d": 23, "kishu": "A-SLOT+ ディスクアップ ULTRAREMIX", "samai": 334, "g": 4126, "deri": 102.7}, {"m": 5, "d": 23, "kishu": "スマスロモンキーターンV", "samai": 301, "g": 3288, "deri": 103.1}, {"m": 5, "d": 23, "kishu": "パチスロひぐらしのなく頃に祭２", "samai": 295, "g": 584, "deri": 116.8}, {"m": 5, "d": 23, "kishu": "Lパチスロうみねこのなく頃に2", "samai": 164, "g": 4277, "deri": 101.3}, {"m": 5, "d": 23, "kishu": "ゴーゴージャグラー３", "samai": 115, "g": 4034, "deri": 101.0}, {"m": 5, "d": 23, "kishu": "スマスロ 東京リベンジャーズ", "samai": 40, "g": 2695, "deri": 100.5}, {"m": 5, "d": 23, "kishu": "ジャグラーガールズSS", "samai": 35, "g": 2842, "deri": 100.4}, {"m": 5, "d": 23, "kishu": "Lパチスロ革命機ヴァルヴレイヴ2", "samai": 21, "g": 4890, "deri": 100.1}, {"m": 5, "d": 23, "kishu": "ファンキージャグラー２ＫＴ", "samai": 17, "g": 4282, "deri": 100.1}, {"m": 5, "d": 23, "kishu": "スマスロ バイオハザードRE:3", "samai": 16, "g": 4185, "deri": 100.1}, {"m": 5, "d": 23, "kishu": "スロット ゾンビランドサガ", "samai": -93, "g": 2387, "deri": 98.7}, {"m": 5, "d": 23, "kishu": "Lパチスロ かぐや様は告らせたい", "samai": -96, "g": 3768, "deri": 99.2}, {"m": 5, "d": 23, "kishu": "アレックス ブライト", "samai": -100, "g": 2493, "deri": 98.1}, {"m": 5, "d": 23, "kishu": "Lパチスロからくりサーカス", "samai": -150, "g": 1003, "deri": 94.8}, {"m": 5, "d": 23, "kishu": "ネオアイムジャグラーEX", "samai": -200, "g": 4525, "deri": 98.2}, {"m": 5, "d": 23, "kishu": "LBパチスロ ヱヴァンゲリヲン～約束の扉～", "samai": -250, "g": 1178, "deri": 91.5}, {"m": 5, "d": 23, "kishu": "新ハナビ", "samai": -250, "g": 4294, "deri": 97.6}, {"m": 5, "d": 23, "kishu": "SHAKE BONUS TRIGGER", "samai": -250, "g": 3937, "deri": 97.4}, {"m": 5, "d": 23, "kishu": "マイジャグラーV", "samai": -250, "g": 5148, "deri": 98.0}, {"m": 5, "d": 23, "kishu": "プリズムナナ", "samai": -250, "g": 771, "deri": 82.3}, {"m": 5, "d": 23, "kishu": "スマスロ モンスターハンターライズ", "samai": -250, "g": 2717, "deri": 94.8}, {"m": 5, "d": 23, "kishu": "スマスロ ミリオンゴッド-神々の軌跡-", "samai": -500, "g": 8345, "deri": 97.8}, {"m": 5, "d": 23, "kishu": "スマスロヨルムンガンド", "samai": -500, "g": 2081, "deri": 89.2}, {"m": 5, "d": 23, "kishu": "Lパチスロ炎炎ノ消防隊2", "samai": -1250, "g": 6563, "deri": 93.6}, {"m": 5, "d": 23, "kishu": "Lパチスロ 機動戦士ガンダムユニコーン 覚醒DRIVE", "samai": -1250, "g": 3638, "deri": 88.0}, {"m": 5, "d": 23, "kishu": "L虚構推理", "samai": -2000, "g": 6042, "deri": 88.9}, {"m": 5, "d": 23, "kishu": "スマスロ スーパーリオエース2", "samai": -2250, "g": 5874, "deri": 87.0}, {"m": 5, "d": 23, "kishu": "Lタクトオーパス デスティニー", "samai": -2250, "g": 6553, "deri": 88.1}, {"m": 5, "d": 23, "kishu": "0", "samai": 979, "g": 4499, "deri": 107.3}, {"m": 5, "d": 23, "kishu": "1", "samai": 236, "g": 4027, "deri": 102.0}, {"m": 5, "d": 23, "kishu": "4", "samai": 729, "g": 3981, "deri": 106.1}, {"m": 5, "d": 23, "kishu": "5", "samai": 422, "g": 4192, "deri": 103.4}, {"m": 5, "d": 23, "kishu": "7", "samai": 146, "g": 4176, "deri": 101.2}, {"m": 5, "d": 23, "kishu": "8", "samai": 120, "g": 4374, "deri": 100.9}, {"m": 5, "d": 23, "kishu": "9", "samai": 651, "g": 4455, "deri": 104.9}, {"m": 5, "d": 22, "kishu": "スマスロ ミリオンゴッド-神々の軌跡-", "samai": 3073, "g": 8915, "deri": 111.5}, {"m": 5, "d": 22, "kishu": "L虚構推理", "samai": 2627, "g": 7903, "deri": 111.1}, {"m": 5, "d": 22, "kishu": "スマスロ鉄拳6", "samai": 2425, "g": 4486, "deri": 118.0}, {"m": 5, "d": 22, "kishu": "スマスロ 東京リベンジャーズ", "samai": 2075, "g": 9207, "deri": 107.5}, {"m": 5, "d": 22, "kishu": "Lスマスロ北斗の拳", "samai": 1864, "g": 3530, "deri": 117.6}, {"m": 5, "d": 22, "kishu": "スマスロ ゴッドイーター リザレクション", "samai": 1828, "g": 4247, "deri": 114.3}, {"m": 5, "d": 22, "kishu": "スマスロ マギアレコード 魔法少女まどか☆マギカ外伝", "samai": 1565, "g": 5497, "deri": 109.5}, {"m": 5, "d": 22, "kishu": "パチスロひぐらしのなく頃に祭２", "samai": 1000, "g": 3709, "deri": 109.0}, {"m": 5, "d": 22, "kishu": "L東京喰種", "samai": 710, "g": 7095, "deri": 103.3}, {"m": 5, "d": 22, "kishu": "Lパチスロ かぐや様は告らせたい", "samai": 623, "g": 2961, "deri": 107.0}, {"m": 5, "d": 22, "kishu": "A-SLOT+ ディスクアップ ULTRAREMIX", "samai": 620, "g": 4321, "deri": 104.8}, {"m": 5, "d": 22, "kishu": "Lタクトオーパス デスティニー", "samai": 605, "g": 7235, "deri": 102.8}, {"m": 5, "d": 22, "kishu": "スマスロ 甲鉄城のカバネリ 海門決戦", "samai": 557, "g": 5915, "deri": 103.1}, {"m": 5, "d": 22, "kishu": "ファンキージャグラー２ＫＴ", "samai": 546, "g": 5535, "deri": 103.3}, {"m": 5, "d": 22, "kishu": "Lパチスロうみねこのなく頃に2", "samai": 486, "g": 3688, "deri": 104.4}, {"m": 5, "d": 22, "kishu": "スマスロモンキーターンV", "samai": 383, "g": 4280, "deri": 103.0}, {"m": 5, "d": 22, "kishu": "アレックス ブライト", "samai": 343, "g": 1989, "deri": 105.8}, {"m": 5, "d": 22, "kishu": "スマスロ スーパーリオエース2", "samai": 280, "g": 5546, "deri": 101.7}, {"m": 5, "d": 22, "kishu": "スマスロヨルムンガンド", "samai": 268, "g": 3184, "deri": 102.8}, {"m": 5, "d": 22, "kishu": "ゴーゴージャグラー３", "samai": 261, "g": 5585, "deri": 101.6}, {"m": 5, "d": 22, "kishu": "ハッピージャグラーＶＩＩＩ", "samai": 223, "g": 4284, "deri": 101.7}, {"m": 5, "d": 22, "kishu": "新ハナビ", "samai": 217, "g": 3456, "deri": 102.1}, {"m": 5, "d": 22, "kishu": "ネオアイムジャグラーEX", "samai": -38, "g": 5250, "deri": 99.8}, {"m": 5, "d": 22, "kishu": "マイジャグラーV", "samai": -88, "g": 5948, "deri": 99.5}, {"m": 5, "d": 22, "kishu": "LBパチスロ ヱヴァンゲリヲン～約束の扉～", "samai": -100, "g": 1688, "deri": 97.7}, {"m": 5, "d": 22, "kishu": "もっと！クレアの秘宝伝　女神の歌声と太陽の子供達", "samai": -150, "g": 1705, "deri": 96.9}, {"m": 5, "d": 22, "kishu": "スマスロ化物語", "samai": -200, "g": 6102, "deri": 98.9}, {"m": 5, "d": 22, "kishu": "ウルトラミラクルジャグラー", "samai": -200, "g": 4421, "deri": 98.3}, {"m": 5, "d": 22, "kishu": "SHAKE BONUS TRIGGER", "samai": -250, "g": 2511, "deri": 96.2}, {"m": 5, "d": 22, "kishu": "Lパチスロからくりサーカス", "samai": -250, "g": 1628, "deri": 93.4}, {"m": 5, "d": 22, "kishu": "スマスロ サンダーV", "samai": -250, "g": 3532, "deri": 95.5}, {"m": 5, "d": 22, "kishu": "ジャグラーガールズSS", "samai": -500, "g": 4678, "deri": 95.0}, {"m": 5, "d": 22, "kishu": "スロット ゾンビランドサガ", "samai": -750, "g": 1935, "deri": 86.2}, {"m": 5, "d": 22, "kishu": "Lパチスロ革命機ヴァルヴレイヴ2", "samai": -750, "g": 8197, "deri": 96.5}, {"m": 5, "d": 22, "kishu": "スマスロバジリスク～甲賀忍法帖～絆2 天膳 BLACK EDITION", "samai": -750, "g": 3403, "deri": 91.4}, {"m": 5, "d": 22, "kishu": "Lパチスロ 機動戦士ガンダムユニコーン 覚醒DRIVE", "samai": -750, "g": 4008, "deri": 92.2}, {"m": 5, "d": 22, "kishu": "プリズムナナ", "samai": -750, "g": 1963, "deri": 83.8}, {"m": 5, "d": 22, "kishu": "スマスロ北斗の拳 転生の章2", "samai": -1000, "g": 5731, "deri": 94.1}, {"m": 5, "d": 22, "kishu": "L無職転生～異世界行ったら本気だす～", "samai": -1000, "g": 4746, "deri": 92.6}, {"m": 5, "d": 22, "kishu": "スマスロ バイオハザードRE:3", "samai": -1000, "g": 4121, "deri": 90.5}, {"m": 5, "d": 22, "kishu": "Lパチスロ炎炎ノ消防隊2", "samai": -1250, "g": 7061, "deri": 93.7}, {"m": 5, "d": 22, "kishu": "スマスロ モンスターハンターライズ", "samai": -1750, "g": 2944, "deri": 78.2}, {"m": 5, "d": 22, "kishu": "L ToLOVEるダークネス TRANCE ver.8.7", "samai": -2000, "g": 6497, "deri": 89.1}, {"m": 5, "d": 22, "kishu": "スマスロ 攻殻機動隊", "samai": -2000, "g": 5011, "deri": 85.3}, {"m": 5, "d": 22, "kishu": "0", "samai": 536, "g": 5254, "deri": 103.4}, {"m": 5, "d": 22, "kishu": "1", "samai": 438, "g": 4949, "deri": 103.0}, {"m": 5, "d": 22, "kishu": "2", "samai": 325, "g": 5348, "deri": 102.0}, {"m": 5, "d": 22, "kishu": "3", "samai": 565, "g": 5311, "deri": 103.5}, {"m": 5, "d": 22, "kishu": "4", "samai": 4, "g": 5415, "deri": 100.0}, {"m": 5, "d": 22, "kishu": "8", "samai": 392, "g": 5289, "deri": 102.5}, {"m": 5, "d": 21, "kishu": "スマスロ 甲鉄城のカバネリ 海門決戦", "samai": 3977, "g": 6698, "deri": 119.8}, {"m": 5, "d": 21, "kishu": "スマスロ モンスターハンターライズ", "samai": 2654, "g": 2785, "deri": 131.8}, {"m": 5, "d": 21, "kishu": "Lタクトオーパス デスティニー", "samai": 2280, "g": 6838, "deri": 111.1}, {"m": 5, "d": 21, "kishu": "スマスロ サンダーV", "samai": 1573, "g": 3962, "deri": 113.2}, {"m": 5, "d": 21, "kishu": "L無職転生～異世界行ったら本気だす～", "samai": 1195, "g": 3907, "deri": 110.2}, {"m": 5, "d": 21, "kishu": "スマスロ化物語", "samai": 1026, "g": 3757, "deri": 109.1}, {"m": 5, "d": 21, "kishu": "スマスロ ゴッドイーター リザレクション", "samai": 932, "g": 2496, "deri": 112.4}, {"m": 5, "d": 21, "kishu": "パチスロひぐらしのなく頃に祭２", "samai": 760, "g": 2554, "deri": 109.9}, {"m": 5, "d": 21, "kishu": "スマスロ マギアレコード 魔法少女まどか☆マギカ外伝", "samai": 691, "g": 3700, "deri": 106.2}, {"m": 5, "d": 21, "kishu": "スマスロモンキーターンV", "samai": 607, "g": 4654, "deri": 104.3}, {"m": 5, "d": 21, "kishu": "Lスマスロ北斗の拳", "samai": 578, "g": 3407, "deri": 105.7}, {"m": 5, "d": 21, "kishu": "スマスロ 攻殻機動隊", "samai": 438, "g": 5117, "deri": 102.9}, {"m": 5, "d": 21, "kishu": "スマスロ 東京リベンジャーズ", "samai": 369, "g": 4096, "deri": 103.0}, {"m": 5, "d": 21, "kishu": "L東京喰種", "samai": 356, "g": 5423, "deri": 102.2}, {"m": 5, "d": 21, "kishu": "Lパチスロうみねこのなく頃に2", "samai": 326, "g": 3051, "deri": 103.6}, {"m": 5, "d": 21, "kishu": "Lパチスロ かぐや様は告らせたい", "samai": 311, "g": 2886, "deri": 103.6}, {"m": 5, "d": 21, "kishu": "マイジャグラーV", "samai": 286, "g": 5874, "deri": 101.6}, {"m": 5, "d": 21, "kishu": "L ToLOVEるダークネス TRANCE ver.8.7", "samai": 258, "g": 3504, "deri": 102.4}, {"m": 5, "d": 21, "kishu": "A-SLOT+ ディスクアップ ULTRAREMIX", "samai": 158, "g": 3448, "deri": 101.5}, {"m": 5, "d": 21, "kishu": "アレックス ブライト", "samai": 113, "g": 1664, "deri": 102.3}, {"m": 5, "d": 21, "kishu": "スマスロ北斗の拳 転生の章2", "samai": 109, "g": 2641, "deri": 101.4}, {"m": 5, "d": 21, "kishu": "もっと！クレアの秘宝伝　女神の歌声と太陽の子供達", "samai": 73, "g": 413, "deri": 105.9}, {"m": 5, "d": 21, "kishu": "L虚構推理", "samai": 67, "g": 2880, "deri": 100.8}, {"m": 5, "d": 21, "kishu": "ネオアイムジャグラーEX", "samai": 42, "g": 4841, "deri": 100.3}, {"m": 5, "d": 21, "kishu": "新ハナビ", "samai": 37, "g": 2083, "deri": 100.6}, {"m": 5, "d": 21, "kishu": "ハッピージャグラーＶＩＩＩ", "samai": 0, "g": 2587, "deri": 100.0}, {"m": 5, "d": 21, "kishu": "ゴーゴージャグラー３", "samai": -28, "g": 4241, "deri": 99.8}, {"m": 5, "d": 21, "kishu": "ジャグラーガールズSS", "samai": -150, "g": 2966, "deri": 98.0}, {"m": 5, "d": 21, "kishu": "ウルトラミラクルジャグラー", "samai": -150, "g": 3578, "deri": 98.2}, {"m": 5, "d": 21, "kishu": "スマスロ鉄拳6", "samai": -200, "g": 808, "deri": 91.3}, {"m": 5, "d": 21, "kishu": "Lパチスロからくりサーカス", "samai": -250, "g": 1038, "deri": 91.0}, {"m": 5, "d": 21, "kishu": "ファンキージャグラー２ＫＴ", "samai": -250, "g": 3815, "deri": 97.3}, {"m": 5, "d": 21, "kishu": "スマスロヨルムンガンド", "samai": -250, "g": 542, "deri": 74.8}, {"m": 5, "d": 21, "kishu": "Lパチスロ 機動戦士ガンダムユニコーン 覚醒DRIVE", "samai": -250, "g": 2308, "deri": 93.9}, {"m": 5, "d": 21, "kishu": "スマスロ スーパーリオエース2", "samai": -250, "g": 5981, "deri": 97.5}, {"m": 5, "d": 21, "kishu": "スマスロ バイオハザードRE:3", "samai": -500, "g": 4891, "deri": 96.4}, {"m": 5, "d": 21, "kishu": "SHAKE BONUS TRIGGER", "samai": -500, "g": 1559, "deri": 88.0}, {"m": 5, "d": 21, "kishu": "LBパチスロ ヱヴァンゲリヲン～約束の扉～", "samai": -500, "g": 1438, "deri": 86.1}, {"m": 5, "d": 21, "kishu": "スマスロバジリスク～甲賀忍法帖～絆2 天膳 BLACK EDITION", "samai": -750, "g": 1470, "deri": 78.8}, {"m": 5, "d": 21, "kishu": "スロット ゾンビランドサガ", "samai": -750, "g": 1828, "deri": 82.2}, {"m": 5, "d": 21, "kishu": "スマスロ ミリオンゴッド-神々の軌跡-", "samai": -1000, "g": 7115, "deri": 95.1}, {"m": 5, "d": 21, "kishu": "プリズムナナ", "samai": -1500, "g": 4268, "deri": 87.2}, {"m": 5, "d": 21, "kishu": "Lパチスロ炎炎ノ消防隊2", "samai": -1500, "g": 5594, "deri": 89.9}, {"m": 5, "d": 21, "kishu": "Lパチスロ革命機ヴァルヴレイヴ2", "samai": -1750, "g": 7502, "deri": 91.7}, {"m": 5, "d": 21, "kishu": "0", "samai": 108, "g": 3822, "deri": 100.9}, {"m": 5, "d": 21, "kishu": "2", "samai": 554, "g": 4569, "deri": 104.0}, {"m": 5, "d": 21, "kishu": "3", "samai": 10, "g": 4117, "deri": 100.1}, {"m": 5, "d": 21, "kishu": "5", "samai": 459, "g": 4326, "deri": 103.5}, {"m": 5, "d": 21, "kishu": "8", "samai": 338, "g": 4686, "deri": 102.4}, {"m": 5, "d": 21, "kishu": "9", "samai": 106, "g": 4127, "deri": 100.9}, {"m": 5, "d": 20, "kishu": "L無職転生～異世界行ったら本気だす～", "samai": 7815, "g": 6051, "deri": 143.1}, {"m": 5, "d": 20, "kishu": "L ToLOVEるダークネス TRANCE ver.8.7", "samai": 2693, "g": 3058, "deri": 129.4}, {"m": 5, "d": 20, "kishu": "スマスロ化物語", "samai": 2218, "g": 6749, "deri": 111.0}, {"m": 5, "d": 20, "kishu": "スマスロ ミリオンゴッド-神々の軌跡-", "samai": 1498, "g": 8015, "deri": 106.2}, {"m": 5, "d": 20, "kishu": "スマスロモンキーターンV", "samai": 1373, "g": 3812, "deri": 112.0}, {"m": 5, "d": 20, "kishu": "スマスロ モンスターハンターライズ", "samai": 1168, "g": 1784, "deri": 121.8}, {"m": 5, "d": 20, "kishu": "スマスロ 甲鉄城のカバネリ 海門決戦", "samai": 1137, "g": 4713, "deri": 108.0}, {"m": 5, "d": 20, "kishu": "パチスロひぐらしのなく頃に祭２", "samai": 955, "g": 3340, "deri": 109.5}, {"m": 5, "d": 20, "kishu": "スマスロ ゴッドイーター リザレクション", "samai": 734, "g": 989, "deri": 124.7}, {"m": 5, "d": 20, "kishu": "A-SLOT+ ディスクアップ ULTRAREMIX", "samai": 692, "g": 3151, "deri": 107.3}, {"m": 5, "d": 20, "kishu": "スマスロ 攻殻機動隊", "samai": 634, "g": 4127, "deri": 105.1}, {"m": 5, "d": 20, "kishu": "スマスロ スーパーリオエース2", "samai": 585, "g": 6128, "deri": 103.2}, {"m": 5, "d": 20, "kishu": "L東京喰種", "samai": 542, "g": 3998, "deri": 104.5}, {"m": 5, "d": 20, "kishu": "ネオアイムジャグラーEX", "samai": 469, "g": 5354, "deri": 102.9}, {"m": 5, "d": 20, "kishu": "LBパチスロ ヱヴァンゲリヲン～約束の扉～", "samai": 455, "g": 1914, "deri": 107.9}, {"m": 5, "d": 20, "kishu": "Lパチスロ革命機ヴァルヴレイヴ2", "samai": 423, "g": 5780, "deri": 102.4}, {"m": 5, "d": 20, "kishu": "Lパチスロうみねこのなく頃に2", "samai": 224, "g": 4838, "deri": 101.5}, {"m": 5, "d": 20, "kishu": "マイジャグラーV", "samai": 206, "g": 5345, "deri": 101.3}, {"m": 5, "d": 20, "kishu": "Lスマスロ北斗の拳", "samai": 206, "g": 1702, "deri": 104.0}, {"m": 5, "d": 20, "kishu": "スマスロ マギアレコード 魔法少女まどか☆マギカ外伝", "samai": 151, "g": 2102, "deri": 102.4}, {"m": 5, "d": 20, "kishu": "スマスロ北斗の拳 転生の章2", "samai": 95, "g": 4165, "deri": 100.8}, {"m": 5, "d": 20, "kishu": "Lパチスロ かぐや様は告らせたい", "samai": -14, "g": 1443, "deri": 99.7}, {"m": 5, "d": 20, "kishu": "ジャグラーガールズSS", "samai": -50, "g": 3499, "deri": 99.5}, {"m": 5, "d": 20, "kishu": "もっと！クレアの秘宝伝　女神の歌声と太陽の子供達", "samai": -83, "g": 180, "deri": 84.6}, {"m": 5, "d": 20, "kishu": "ゴーゴージャグラー３", "samai": -100, "g": 4356, "deri": 99.2}, {"m": 5, "d": 20, "kishu": "SHAKE BONUS TRIGGER", "samai": -100, "g": 3483, "deri": 98.9}, {"m": 5, "d": 20, "kishu": "プリズムナナ", "samai": -200, "g": 1357, "deri": 94.3}, {"m": 5, "d": 20, "kishu": "Lパチスロからくりサーカス", "samai": -250, "g": 1717, "deri": 94.8}, {"m": 5, "d": 20, "kishu": "スマスロ鉄拳6", "samai": -250, "g": 381, "deri": 69.5}, {"m": 5, "d": 20, "kishu": "新ハナビ", "samai": -250, "g": 1039, "deri": 88.2}, {"m": 5, "d": 20, "kishu": "スマスロ サンダーV", "samai": -250, "g": 3049, "deri": 95.7}, {"m": 5, "d": 20, "kishu": "スマスロ 東京リベンジャーズ", "samai": -250, "g": 2844, "deri": 94.5}, {"m": 5, "d": 20, "kishu": "アレックス ブライト", "samai": -500, "g": 2024, "deri": 91.4}, {"m": 5, "d": 20, "kishu": "Lパチスロ 機動戦士ガンダムユニコーン 覚醒DRIVE", "samai": -500, "g": 1774, "deri": 90.0}, {"m": 5, "d": 20, "kishu": "ファンキージャグラー２ＫＴ", "samai": -500, "g": 3743, "deri": 95.2}, {"m": 5, "d": 20, "kishu": "Lパチスロ炎炎ノ消防隊2", "samai": -500, "g": 4364, "deri": 95.6}, {"m": 5, "d": 20, "kishu": "スマスロ バイオハザードRE:3", "samai": -500, "g": 2737, "deri": 92.7}, {"m": 5, "d": 20, "kishu": "スロット ゾンビランドサガ", "samai": -500, "g": 1075, "deri": 80.7}, {"m": 5, "d": 20, "kishu": "Lタクトオーパス デスティニー", "samai": -500, "g": 6161, "deri": 96.2}, {"m": 5, "d": 20, "kishu": "ウルトラミラクルジャグラー", "samai": -500, "g": 3366, "deri": 92.6}, {"m": 5, "d": 20, "kishu": "スマスロヨルムンガンド", "samai": -750, "g": 1240, "deri": 79.8}, {"m": 5, "d": 20, "kishu": "ハッピージャグラーＶＩＩＩ", "samai": -750, "g": 3441, "deri": 91.7}, {"m": 5, "d": 20, "kishu": "スマスロバジリスク～甲賀忍法帖～絆2 天膳 BLACK EDITION", "samai": -1000, "g": 1098, "deri": 64.0}, {"m": 5, "d": 20, "kishu": "L虚構推理", "samai": -1250, "g": 4672, "deri": 90.5}, {"m": 5, "d": 20, "kishu": "0", "samai": 181, "g": 4004, "deri": 101.5}, {"m": 5, "d": 20, "kishu": "1", "samai": 44, "g": 3854, "deri": 100.4}, {"m": 5, "d": 20, "kishu": "3", "samai": 489, "g": 3446, "deri": 104.7}, {"m": 5, "d": 20, "kishu": "4", "samai": 163, "g": 3604, "deri": 101.5}, {"m": 5, "d": 20, "kishu": "5", "samai": 452, "g": 3895, "deri": 103.9}, {"m": 5, "d": 20, "kishu": "6", "samai": 59, "g": 3137, "deri": 100.6}, {"m": 5, "d": 20, "kishu": "7", "samai": 327, "g": 3546, "deri": 103.1}, {"m": 5, "d": 20, "kishu": "8", "samai": 669, "g": 4409, "deri": 105.1}, {"m": 5, "d": 20, "kishu": "9", "samai": 168, "g": 3812, "deri": 101.5}]}